{
  "lastUpdated": "2026-05-06T10:52:57.264923+00:00",
  "lastUpdatedDisplay": "May 06, 2026 \u2014 10:52 AM UTC",
  "articleCount": 75,
  "currentRegime": "Reflation",
  "currentRegimeColor": "#00e5ff",
  "regimeConfidence": "MEDIUM",
  "regimeAsOf": "2026-05-01T15:30:00-05:00",
  "summary": {
    "macroSummary": "Markets surged on reports of potential US-Iran peace deal progress, with global stocks hitting records while oil prices declined sharply from geopolitical risk premium unwinding. Bitcoin rallied past $80K amid ETF inflows and broader risk-on sentiment, while bond yields fell and the dollar weakened on Middle East de-escalation hopes.",
    "regimePressure": "PRESSURING",
    "regimePressureReason": "The Iran peace deal reports are unwinding the oil shock premium that was a key pillar of the current Reflation regime, with oil sliding and bond yields falling as stagflationary pressures ease.",
    "thresholdWatches": [
      {
        "indicator": "Oil (WTI)",
        "level": "< $115",
        "signal": "Oil sliding on Iran peace deal reports suggests the war premium is unwinding"
      },
      {
        "indicator": "DXY",
        "level": "approaching 100",
        "signal": "Dollar tumbling on Iran deal hopes and yen intervention speculation"
      }
    ],
    "keySignals": [
      {
        "signal": "Oil prices sliding sharply on Iran peace deal reports unwinds the geopolitical risk premium supporting the Reflation thesis",
        "tag": "CONTRADICTS"
      },
      {
        "signal": "US Treasury yields falling across the curve as Middle East tensions ease reduces stagflationary pressure",
        "tag": "CONTRADICTS"
      },
      {
        "signal": "Dollar weakening significantly against yen on intervention chatter and Iran deal optimism",
        "tag": "THRESHOLD_WATCH"
      },
      {
        "signal": "Global stocks surging to records on AI euphoria and geopolitical de-escalation supports risk-on sentiment",
        "tag": "SUPPORTS"
      },
      {
        "signal": "Bitcoin ETFs seeing massive inflows with BTC above $80K indicates continued crypto momentum",
        "tag": "NEUTRAL"
      }
    ],
    "actionItems": [
      "Monitor oil prices closely - sustained weakness below current levels would challenge the Iran-war shock embedded in regime",
      "BMNR ladder may face headwinds if crypto rally continues but prepare for volatility if Iran deal falls through",
      "Consider reducing cyclical exposure if oil weakness persists and bond yields continue falling"
    ]
  },
  "articles": [
    {
      "title": "End in sight?",
      "source": "reuters",
      "color": "#ff6d00",
      "timestamp": "2026-05-06T10:49:33+00:00",
      "timeDisplay": "10:49 AM",
      "link": "https://www.tradingview.com/news/reuters.com,2026:newsml_L6N41J0IH:0-end-in-sight/"
    },
    {
      "title": "Bitcoin ETFs add nearly $1B as BTC surges past $80K in multi-day rally",
      "source": "cointelegraph",
      "color": "#00e5ff",
      "timestamp": "2026-05-06T10:40:09+00:00",
      "timeDisplay": "10:40 AM",
      "link": "https://www.tradingview.com/news/cointelegraph:b9a175434094b:0-bitcoin-etfs-add-nearly-1b-as-btc-surges-past-80k-in-multi-day-rally/"
    },
    {
      "title": "MSTR Stock Slips Even With Bitcoin Above $81,900 \u2013 Michael Saylor\u2019s \u2018Never Sell\u2019 Pivot Gets Wall Street Support",
      "source": "stocktwits",
      "color": "#00e5ff",
      "timestamp": "2026-05-06T10:24:56+00:00",
      "timeDisplay": "10:24 AM",
      "link": "https://www.tradingview.com/news/stocktwits:64e091d08094b:0/"
    },
    {
      "title": "Ethereum co-founder Lubin backs ETH treasury firms, calls DATs \u2018profound innovation\u2019",
      "source": "the_block",
      "color": "#00e5ff",
      "timestamp": "2026-05-06T10:20:52+00:00",
      "timeDisplay": "10:20 AM",
      "link": "https://www.tradingview.com/news/the_block:fe50a9972094b:0-ethereum-co-founder-lubin-backs-eth-treasury-firms-calls-dats-profound-innovation/"
    },
    {
      "title": "Global stocks surge and oil slides on Iran peace deal report",
      "source": "reuters",
      "color": "#ff6d00",
      "timestamp": "2026-05-06T10:10:14+00:00",
      "timeDisplay": "10:10 AM",
      "link": "https://www.tradingview.com/news/reuters.com,2026:newsml_L1N41J0DS:0-global-stocks-surge-and-oil-slides-on-iran-peace-deal-report/"
    },
    {
      "title": "Stunning US profit strength ignites stocks' charge to record peaks",
      "source": "reuters",
      "color": "#ff6d00",
      "timestamp": "2026-05-06T10:00:00+00:00",
      "timeDisplay": "10:00 AM",
      "link": "https://www.tradingview.com/news/reuters.com,2026:newsml_L6N41H0ZU:0-stunning-us-profit-strength-ignites-stocks-charge-to-record-peaks/"
    },
    {
      "title": "US long bonds over 5% - buy or beware?: Mike Dolan",
      "source": "reuters",
      "color": "#ff6d00",
      "timestamp": "2026-05-06T10:00:00+00:00",
      "timeDisplay": "10:00 AM",
      "link": "https://www.tradingview.com/news/reuters.com,2026:newsml_L8N41C2VY:0-us-long-bonds-over-5-buy-or-beware-mike-dolan/"
    },
    {
      "title": "Bitcoin Hits Fresh 3-Month High on U.S.-Iran Peace Deal Hopes \u2014 Market Talk",
      "source": "dow-jones",
      "color": "#00e5ff",
      "timestamp": "2026-05-06T09:57:00+00:00",
      "timeDisplay": "9:57 AM",
      "link": "https://www.tradingview.com/news/DJN_DN20260506003320:0/"
    },
    {
      "title": "XRP News: Garlinghouse \u201cI\u2019ve never been an XRP maxi\u201d Comment Could Supress XRP Price",
      "source": "cryptonews",
      "color": "#00e5ff",
      "timestamp": "2026-05-06T09:52:31+00:00",
      "timeDisplay": "9:52 AM",
      "link": "https://www.tradingview.com/news/cryptonews:9cfb4266e094b:0-xrp-news-garlinghouse-i-ve-never-been-an-xrp-maxi-comment-could-supress-xrp-price/"
    },
    {
      "title": "Gilt Yields Fall on Prospects of Resolution to Middle East Conflict \u2014 Market Talk",
      "source": "dow-jones",
      "color": "#00e5ff",
      "timestamp": "2026-05-06T09:51:00+00:00",
      "timeDisplay": "9:51 AM",
      "link": "https://www.tradingview.com/news/DJN_DN20260506003286:0/"
    },
    {
      "title": "Gold Prices to Remain Supported by Solid Demand \u2014 Market Talk",
      "source": "dow-jones",
      "color": "#00e5ff",
      "timestamp": "2026-05-06T09:50:00+00:00",
      "timeDisplay": "9:50 AM",
      "link": "https://www.tradingview.com/news/DJN_DN20260506003278:0/"
    },
    {
      "title": "US Crude Stockpiles Fall the Most in About 3 Months: API",
      "source": "trading-economics",
      "color": "#00e5ff",
      "timestamp": "2026-05-06T09:42:18+00:00",
      "timeDisplay": "9:42 AM",
      "link": "https://www.tradingview.com/news/te_news:548319:0-us-crude-stockpiles-fall-the-most-in-about-3-months-api/"
    },
    {
      "title": "Michael Saylor said he would never sell bitcoin. Now he says he might.",
      "source": "market-watch",
      "color": "#00e5ff",
      "timestamp": "2026-05-06T09:32:00+00:00",
      "timeDisplay": "9:32 AM",
      "link": "https://www.tradingview.com/news/DJN_SN20260506006613:0/"
    },
    {
      "title": "Global Bond Yields, Dollar Slide on Expectation of Middle East De-Escalation \u2014 Market Talk",
      "source": "dow-jones",
      "color": "#00e5ff",
      "timestamp": "2026-05-06T09:32:00+00:00",
      "timeDisplay": "9:32 AM",
      "link": "https://www.tradingview.com/news/DJN_DN20260506003174:0/"
    },
    {
      "title": "Oil Slides on Report of Peace Deal Progress \u2014 Market Talk",
      "source": "dow-jones",
      "color": "#00e5ff",
      "timestamp": "2026-05-06T09:24:00+00:00",
      "timeDisplay": "9:24 AM",
      "link": "https://www.tradingview.com/news/DJN_DN20260506003099:0/"
    },
    {
      "title": "Oil Extends Losses on Iran Deal Hopes",
      "source": "trading-economics",
      "color": "#00e5ff",
      "timestamp": "2026-05-06T09:21:58+00:00",
      "timeDisplay": "9:21 AM",
      "link": "https://www.tradingview.com/news/te_news:548307:0-oil-extends-losses-on-iran-deal-hopes/"
    },
    {
      "title": "Global stocks surge on Iran peace hopes and AI euphoria",
      "source": "reuters",
      "color": "#ff6d00",
      "timestamp": "2026-05-06T08:30:58+00:00",
      "timeDisplay": "8:30 AM",
      "link": "https://www.tradingview.com/news/reuters.com,2026:newsml_L1N41J0AE:0-global-stocks-surge-on-iran-peace-hopes-and-ai-euphoria/"
    },
    {
      "title": "Dollar tumbles against yen as intervention chatter swirls, optimism grows for US-Iran deal",
      "source": "reuters",
      "color": "#ff6d00",
      "timestamp": "2026-05-06T08:26:01+00:00",
      "timeDisplay": "8:26 AM",
      "link": "https://www.tradingview.com/news/reuters.com,2026:newsml_L6N41J0BE:0-dollar-tumbles-against-yen-as-intervention-chatter-swirls-optimism-grows-for-us-iran-deal/"
    },
    {
      "title": "Strategy Posts Wider Loss as Bitcoin Holdings Hit $64 Billion. The Stock Falls. \u2014 Barrons.com",
      "source": "dow-jones",
      "color": "#00e5ff",
      "timestamp": "2026-05-06T08:22:00+00:00",
      "timeDisplay": "8:22 AM",
      "link": "https://www.tradingview.com/news/DJN_DN20260505016006:0/"
    },
    {
      "title": "Ethereum Founder Vitalik Says Five Banks on One Chain Is Not a Blockchain Solution",
      "source": "coinpedia",
      "color": "#00e5ff",
      "timestamp": "2026-05-06T08:05:19+00:00",
      "timeDisplay": "8:05 AM",
      "link": "https://www.tradingview.com/news/coinpedia:ef7c9fa7f094b:0-ethereum-founder-vitalik-says-five-banks-on-one-chain-is-not-a-blockchain-solution/"
    },
    {
      "title": "Colombian president seeks to transform the Caribbean into bitcoin mining hub",
      "source": "the_block",
      "color": "#00e5ff",
      "timestamp": "2026-05-06T07:50:43+00:00",
      "timeDisplay": "7:50 AM",
      "link": "https://www.tradingview.com/news/the_block:2f97c437a094b:0-colombian-president-seeks-to-transform-the-caribbean-into-bitcoin-mining-hub/"
    },
    {
      "title": "Gilt Yields Fall as Oil Prices Decline \u2014 Market Talk",
      "source": "dow-jones",
      "color": "#00e5ff",
      "timestamp": "2026-05-06T07:27:00+00:00",
      "timeDisplay": "7:27 AM",
      "link": "https://www.tradingview.com/news/DJN_DN20260506002424:0/"
    },
    {
      "title": "Eurozone Government Bond Yields Fall, Track U.S. Treasury Moves \u2014 Market Talk",
      "source": "dow-jones",
      "color": "#00e5ff",
      "timestamp": "2026-05-06T07:20:00+00:00",
      "timeDisplay": "7:20 AM",
      "link": "https://www.tradingview.com/news/DJN_DN20260506002396:0/"
    },
    {
      "title": "Oil Eases as U.S. Appears to Pull Back From Iran Escalation \u2014 Market Talk",
      "source": "dow-jones",
      "color": "#00e5ff",
      "timestamp": "2026-05-06T07:17:00+00:00",
      "timeDisplay": "7:17 AM",
      "link": "https://www.tradingview.com/news/DJN_DN20260506002385:0/"
    },
    {
      "title": "Why Is Bitcoin Price Going Up? BTC Tests $82K 200 EMA And Three-Months Highs",
      "source": "financemagnates",
      "color": "#00e5ff",
      "timestamp": "2026-05-06T07:13:33+00:00",
      "timeDisplay": "7:13 AM",
      "link": "https://www.tradingview.com/news/financemagnates:2236c358e094b:0-why-is-bitcoin-price-going-up-btc-tests-82k-200-ema-and-three-months-highs/"
    },
    {
      "title": "Bitcoin Falls Slightly But Stays Above $80K \u2014 Market Talk",
      "source": "dow-jones",
      "color": "#00e5ff",
      "timestamp": "2026-05-06T07:05:00+00:00",
      "timeDisplay": "7:05 AM",
      "link": "https://www.tradingview.com/news/DJN_DN20260506002309:0/"
    },
    {
      "title": "Colombian president says Bitcoin mining could transform country's Caribbean coast",
      "source": "cointelegraph",
      "color": "#00e5ff",
      "timestamp": "2026-05-06T06:43:07+00:00",
      "timeDisplay": "6:43 AM",
      "link": "https://www.tradingview.com/news/cointelegraph:916b0d03f094b:0-colombian-president-says-bitcoin-mining-could-transform-country-s-caribbean-coast/"
    },
    {
      "title": "Dollar Falls on U.S.-Iran Peace Deal Hopes, Stronger Yen \u2014 Market Talk",
      "source": "dow-jones",
      "color": "#00e5ff",
      "timestamp": "2026-05-06T06:41:00+00:00",
      "timeDisplay": "6:41 AM",
      "link": "https://www.tradingview.com/news/DJN_DN20260506002161:0/"
    },
    {
      "title": "US 10Y Yield Falls on Iran Deal Optimism",
      "source": "trading-economics",
      "color": "#00e5ff",
      "timestamp": "2026-05-06T06:39:39+00:00",
      "timeDisplay": "6:39 AM",
      "link": "https://www.tradingview.com/news/te_news:548181:0-us-10y-yield-falls-on-iran-deal-optimism/"
    },
    {
      "title": "Occidental Q1 Profit Surges On Gain From OxyChem Sale",
      "source": "dpa_afx",
      "color": "#00e5ff",
      "timestamp": "2026-05-06T06:30:59+00:00",
      "timeDisplay": "6:30 AM",
      "link": "https://www.tradingview.com/news/dpa_afx:38ddb4cb964ad:0-occidental-q1-profit-surges-on-gain-from-oxychem-sale/"
    },
    {
      "title": "U.S. Treasury Yields Fall, Markets Bet on Middle East Resolution \u2014 Market Talk",
      "source": "dow-jones",
      "color": "#00e5ff",
      "timestamp": "2026-05-06T06:19:00+00:00",
      "timeDisplay": "6:19 AM",
      "link": "https://www.tradingview.com/news/DJN_DN20260506001926:0/"
    },
    {
      "title": "Why Bitcoin\u2019s 20% Price Rally Reads Bearish Underneath",
      "source": "beincrypto",
      "color": "#00e5ff",
      "timestamp": "2026-05-06T05:58:01+00:00",
      "timeDisplay": "5:58 AM",
      "link": "https://www.tradingview.com/news/beincrypto:0f9ca739a094b:0-why-bitcoin-s-20-price-rally-reads-bearish-underneath/"
    },
    {
      "title": "Asia markets hit records on AI euphoria, yen surges again",
      "source": "reuters",
      "color": "#ff6d00",
      "timestamp": "2026-05-06T05:48:33+00:00",
      "timeDisplay": "5:48 AM",
      "link": "https://www.tradingview.com/news/reuters.com,2026:newsml_L6N41J06J:0-asia-markets-hit-records-on-ai-euphoria-yen-surges-again/"
    },
    {
      "title": "Small caps put on their best monthly showing since 2020. Bank of America says there's more upside ahead",
      "source": "cnbctv",
      "color": "#00e5ff",
      "timestamp": "2026-05-06T05:32:06+00:00",
      "timeDisplay": "5:32 AM",
      "link": "https://www.tradingview.com/news/cnbctv:fcbb62c9d094b:0/"
    },
    {
      "title": "Dollar eases as US-Iran deal hopes grow, yen firms on intervention speculation",
      "source": "reuters",
      "color": "#ff6d00",
      "timestamp": "2026-05-06T05:06:10+00:00",
      "timeDisplay": "5:06 AM",
      "link": "https://www.tradingview.com/news/reuters.com,2026:newsml_L1N41J03B:0-dollar-eases-as-us-iran-deal-hopes-grow-yen-firms-on-intervention-speculation/"
    },
    {
      "title": "Bitcoin Breaks $80,000, But On-Chain Activity Signals A Silent Warning",
      "source": "newsbtc",
      "color": "#00e5ff",
      "timestamp": "2026-05-06T05:00:00+00:00",
      "timeDisplay": "5:00 AM",
      "link": "https://www.tradingview.com/news/newsbtc:65a0abae9094b:0-bitcoin-breaks-80-000-but-on-chain-activity-signals-a-silent-warning/"
    },
    {
      "title": "Suncor Energy Q1 Net Income Rises",
      "source": "dpa_afx",
      "color": "#00e5ff",
      "timestamp": "2026-05-06T04:59:55+00:00",
      "timeDisplay": "4:59 AM",
      "link": "https://www.tradingview.com/news/dpa_afx:656dca02e9920:0-suncor-energy-q1-net-income-rises/"
    },
    {
      "title": "Yen jumps abruptly as intervention speculation swirls",
      "source": "reuters",
      "color": "#ff6d00",
      "timestamp": "2026-05-06T04:55:23+00:00",
      "timeDisplay": "4:55 AM",
      "link": "https://www.tradingview.com/news/reuters.com,2026:newsml_L1N41J03F:0-yen-jumps-abruptly-as-intervention-speculation-swirls/"
    },
    {
      "title": "Strategy Q1 2026: Saylor Shocks Crypto With Talk of Selling Bitcoin to Pay Dividends",
      "source": "coinpedia",
      "color": "#00e5ff",
      "timestamp": "2026-05-06T04:38:01+00:00",
      "timeDisplay": "4:38 AM",
      "link": "https://www.tradingview.com/news/coinpedia:48835c3ac094b:0-strategy-q1-2026-saylor-shocks-crypto-with-talk-of-selling-bitcoin-to-pay-dividends/"
    },
    {
      "title": "Yen jumps suddenly, last up 1%",
      "source": "reuters",
      "color": "#ff6d00",
      "timestamp": "2026-05-06T04:31:38+00:00",
      "timeDisplay": "4:31 AM",
      "link": "https://www.tradingview.com/news/reuters.com,2026:newsml_L4N41J0AN:0-yen-jumps-suddenly-last-up-1/"
    },
    {
      "title": "Stocks surge in Seoul as Samsung surpasses Berkshire",
      "source": "reuters",
      "color": "#ff6d00",
      "timestamp": "2026-05-06T04:30:00+00:00",
      "timeDisplay": "4:30 AM",
      "link": "https://www.tradingview.com/news/reuters.com,2026:newsml_L6N41J04O:0-stocks-surge-in-seoul-as-samsung-surpasses-berkshire/"
    },
    {
      "title": "WEDNESDAY WHITE HOUSE SCHEDULE - Subject to additions during the day",
      "source": "macenews",
      "color": "#00e5ff",
      "timestamp": "2026-05-06T04:23:00+00:00",
      "timeDisplay": "4:23 AM",
      "link": "https://www.tradingview.com/news/macenews:b2182c018094b:0-wednesday-white-house-schedule-subject-to-additions-during-the-day/"
    },
    {
      "title": "Strategy could sell Bitcoin \u2018to inoculate the market,\u2019 Michael Saylor says",
      "source": "cointelegraph",
      "color": "#00e5ff",
      "timestamp": "2026-05-06T04:09:33+00:00",
      "timeDisplay": "4:09 AM",
      "link": "https://www.tradingview.com/news/cointelegraph:0f7067009094b:0-strategy-could-sell-bitcoin-to-inoculate-the-market-michael-saylor-says/"
    },
    {
      "title": "Bitcoin Watch: A Daily Close Above This Key Level Could Push BTC Toward $94,000",
      "source": "newsbtc",
      "color": "#00e5ff",
      "timestamp": "2026-05-06T04:00:13+00:00",
      "timeDisplay": "4:00 AM",
      "link": "https://www.tradingview.com/news/newsbtc:b4926c20c094b:0-bitcoin-watch-a-daily-close-above-this-key-level-could-push-btc-toward-94-000/"
    },
    {
      "title": "Ethereum Price On Verge Of Breakout, Can Bulls Seize Control?",
      "source": "newsbtc",
      "color": "#00e5ff",
      "timestamp": "2026-05-06T03:28:48+00:00",
      "timeDisplay": "3:28 AM",
      "link": "https://www.tradingview.com/news/newsbtc:e9c97ab7c094b:0-ethereum-price-on-verge-of-breakout-can-bulls-seize-control/"
    },
    {
      "title": "China's yuan firms against dollar on Iran deal hopes, robust economic data",
      "source": "reuters",
      "color": "#ff6d00",
      "timestamp": "2026-05-06T03:22:04+00:00",
      "timeDisplay": "3:22 AM",
      "link": "https://www.tradingview.com/news/reuters.com,2026:newsml_L1N41J026:0-china-s-yuan-firms-against-dollar-on-iran-deal-hopes-robust-economic-data/"
    },
    {
      "title": "Bitcoin Price Keeps $80K Support, Can Bulls Extend Rally Soon?",
      "source": "newsbtc",
      "color": "#00e5ff",
      "timestamp": "2026-05-06T03:01:29+00:00",
      "timeDisplay": "3:01 AM",
      "link": "https://www.tradingview.com/news/newsbtc:22dead1ec094b:0-bitcoin-price-keeps-80k-support-can-bulls-extend-rally-soon/"
    },
    {
      "title": "Strategy likely to sell bitcoin to cover STRC dividends, Michael Saylor says",
      "source": "the_block",
      "color": "#00e5ff",
      "timestamp": "2026-05-06T02:58:44+00:00",
      "timeDisplay": "2:58 AM",
      "link": "https://www.tradingview.com/news/the_block:3300a1908094b:0-strategy-likely-to-sell-bitcoin-to-cover-strc-dividends-michael-saylor-says/"
    },
    {
      "title": "Bitcoin holds $81K amid flat derivatives markets: Is rally sustainable?",
      "source": "cointelegraph",
      "color": "#00e5ff",
      "timestamp": "2026-05-06T02:48:53+00:00",
      "timeDisplay": "2:48 AM",
      "link": "https://www.tradingview.com/news/cointelegraph:61c41c6a3094b:0-bitcoin-holds-81k-amid-flat-derivatives-markets-is-rally-sustainable/"
    },
    {
      "title": "Oil Market Under Renewed Selling Pressure \u2014 Market Talk",
      "source": "dow-jones",
      "color": "#00e5ff",
      "timestamp": "2026-05-06T02:42:00+00:00",
      "timeDisplay": "2:42 AM",
      "link": "https://www.tradingview.com/news/DJN_DN20260505017361:0/"
    },
    {
      "title": "MSTR Shares Fall as MicroStrategy Weighs Potential Bitcoin Sale",
      "source": "beincrypto",
      "color": "#00e5ff",
      "timestamp": "2026-05-06T02:39:01+00:00",
      "timeDisplay": "2:39 AM",
      "link": "https://www.tradingview.com/news/beincrypto:27d30e74a094b:0-mstr-shares-fall-as-microstrategy-weighs-potential-bitcoin-sale/"
    },
    {
      "title": "US oil biased to fall toward $95.70",
      "source": "reuters",
      "color": "#ff6d00",
      "timestamp": "2026-05-06T02:30:31+00:00",
      "timeDisplay": "2:30 AM",
      "link": "https://www.tradingview.com/news/reuters.com,2026:newsml_L1N41J01P:0-us-oil-biased-to-fall-toward-95-70/"
    },
    {
      "title": "Institutions Are Buying 6x Bitcoin\u2019s Daily Supply: Is $96,000 Next?",
      "source": "newsbtc",
      "color": "#00e5ff",
      "timestamp": "2026-05-06T02:30:05+00:00",
      "timeDisplay": "2:30 AM",
      "link": "https://www.tradingview.com/news/newsbtc:446a8771f094b:0-institutions-are-buying-6x-bitcoin-s-daily-supply-is-96-000-next/"
    },
    {
      "title": "Gold Futures Rise Amid Easing Middle East Tensions \u2014 Market Talk",
      "source": "dow-jones",
      "color": "#00e5ff",
      "timestamp": "2026-05-06T02:02:00+00:00",
      "timeDisplay": "2:02 AM",
      "link": "https://www.tradingview.com/news/DJN_DN20260505017298:0/"
    },
    {
      "title": "Dollar Slides on Iran Deal Optimism",
      "source": "trading-economics",
      "color": "#00e5ff",
      "timestamp": "2026-05-06T01:31:51+00:00",
      "timeDisplay": "1:31 AM",
      "link": "https://www.tradingview.com/news/te_news:548067:0-dollar-slides-on-iran-deal-optimism/"
    },
    {
      "title": "Asia markets hit records on AI euphoria, Iran peace hopes",
      "source": "reuters",
      "color": "#ff6d00",
      "timestamp": "2026-05-06T01:31:26+00:00",
      "timeDisplay": "1:31 AM",
      "link": "https://www.tradingview.com/news/reuters.com,2026:newsml_L6N41J00Y:0-asia-markets-hit-records-on-ai-euphoria-iran-peace-hopes/"
    },
    {
      "title": "Dollar eases as US-Iran deal hopes grow, yen drifts",
      "source": "reuters",
      "color": "#ff6d00",
      "timestamp": "2026-05-06T01:00:03+00:00",
      "timeDisplay": "1:00 AM",
      "link": "https://www.tradingview.com/news/reuters.com,2026:newsml_L4N41J01X:0-dollar-eases-as-us-iran-deal-hopes-grow-yen-drifts/"
    },
    {
      "title": "Commodities intraday targets/key levels",
      "source": "reuters",
      "color": "#ff6d00",
      "timestamp": "2026-05-06T00:55:16+00:00",
      "timeDisplay": "12:55 AM",
      "link": "https://www.tradingview.com/news/reuters.com,2026:newsml_L1N41J00I:0-commodities-intraday-targets-key-levels/"
    },
    {
      "title": "Oil Falls on Hopes of U.S.-Iran Peace Deal \u2014 Market Talk",
      "source": "dow-jones",
      "color": "#00e5ff",
      "timestamp": "2026-05-06T00:11:00+00:00",
      "timeDisplay": "12:11 AM",
      "link": "https://www.tradingview.com/news/DJN_DN20260505017097:0/"
    },
    {
      "title": "Key facts: ETH Reserves Record Low; Bitmine Stakes 190.8K ETH; ETH $2,383",
      "source": "tradingview",
      "color": "#00e5ff",
      "timestamp": "2026-05-06T00:04:11+00:00",
      "timeDisplay": "12:04 AM",
      "link": "https://www.tradingview.com/news/tradingview:8e6b3d88b85a3:0-key-facts-eth-reserves-record-low-bitmine-stakes-190-8k-eth-eth-2-383/"
    },
    {
      "title": "Gold Extends Gains for a Second Session",
      "source": "trading-economics",
      "color": "#00e5ff",
      "timestamp": "2026-05-05T23:50:05+00:00",
      "timeDisplay": "11:50 PM",
      "link": "https://www.tradingview.com/news/te_news:548035:0-gold-extends-gains-for-a-second-session/"
    },
    {
      "title": "Gold Rises; Trump Pauses 'Project Freedom' to See if Iran Deal Can Be Finalized \u2014 Market Talk",
      "source": "dow-jones",
      "color": "#00e5ff",
      "timestamp": "2026-05-05T23:39:00+00:00",
      "timeDisplay": "11:39 PM",
      "link": "https://www.tradingview.com/news/DJN_DN20260505016979:0/"
    },
    {
      "title": "Oil Declines as US Winds Down Iran Offensive",
      "source": "trading-economics",
      "color": "#00e5ff",
      "timestamp": "2026-05-05T23:31:19+00:00",
      "timeDisplay": "11:31 PM",
      "link": "https://www.tradingview.com/news/te_news:548031:0-oil-declines-as-us-winds-down-iran-offensive/"
    },
    {
      "title": "Ethereum Withdrawals From Exchanges Just Hit An 8-Month Low: Find Out What Investors Are Waiting For",
      "source": "newsbtc",
      "color": "#00e5ff",
      "timestamp": "2026-05-05T22:30:47+00:00",
      "timeDisplay": "10:30 PM",
      "link": "https://www.tradingview.com/news/newsbtc:1b7a44eee094b:0-ethereum-withdrawals-from-exchanges-just-hit-an-8-month-low-find-out-what-investors-are-waiting-for/"
    },
    {
      "title": "Wall Street stocks touch records on upbeat earnings, dip in oil",
      "source": "reuters",
      "color": "#ff6d00",
      "timestamp": "2026-05-05T20:37:48+00:00",
      "timeDisplay": "8:37 PM",
      "link": "https://www.tradingview.com/news/reuters.com,2026:newsml_L1N41I18J:0-wall-street-stocks-touch-records-on-upbeat-earnings-dip-in-oil/"
    },
    {
      "title": "Chips ahoy: Semiconductors boost Nasdaq, S&P 500 to fresh all-time closing highs",
      "source": "reuters",
      "color": "#ff6d00",
      "timestamp": "2026-05-05T20:13:53+00:00",
      "timeDisplay": "8:13 PM",
      "link": "https://www.tradingview.com/news/reuters.com,2026:newsml_L6N41I14F:0-chips-ahoy-semiconductors-boost-nasdaq-s-p-500-to-fresh-all-time-closing-highs/"
    },
    {
      "title": "Dollar Firms as Geopolitical Risks Remain",
      "source": "barchart",
      "color": "#00e5ff",
      "timestamp": "2026-05-05T19:32:59+00:00",
      "timeDisplay": "7:32 PM",
      "link": "https://www.tradingview.com/news/barchart:f8b699938094b:0-dollar-firms-as-geopolitical-risks-remain/"
    },
    {
      "title": "Dollar softens as Middle East ceasefire holds",
      "source": "reuters",
      "color": "#ff6d00",
      "timestamp": "2026-05-05T18:40:00+00:00",
      "timeDisplay": "6:40 PM",
      "link": "https://www.tradingview.com/news/reuters.com,2026:newsml_L1N41I120:0-dollar-softens-as-middle-east-ceasefire-holds/"
    },
    {
      "title": "Stocks gain as investors take heart from upbeat earnings, dip in oil",
      "source": "reuters",
      "color": "#ff6d00",
      "timestamp": "2026-05-05T18:13:19+00:00",
      "timeDisplay": "6:13 PM",
      "link": "https://www.tradingview.com/news/reuters.com,2026:newsml_L1N41I112:0-stocks-gain-as-investors-take-heart-from-upbeat-earnings-dip-in-oil/"
    },
    {
      "title": "Bitmine Just Crossed $10 Billion In Staked Ethereum \u2013 88% of Everything It Owns Is Now Locked In",
      "source": "newsbtc",
      "color": "#00e5ff",
      "timestamp": "2026-05-05T18:00:43+00:00",
      "timeDisplay": "6:00 PM",
      "link": "https://www.tradingview.com/news/newsbtc:2a048fe80094b:0-bitmine-just-crossed-10-billion-in-staked-ethereum-88-of-everything-it-owns-is-now-locked-in/"
    },
    {
      "title": "Concentrated US markets push global diversification back into focus - Nuveen\u00a0",
      "source": "reuters",
      "color": "#ff6d00",
      "timestamp": "2026-05-05T17:02:39+00:00",
      "timeDisplay": "5:02 PM",
      "link": "https://www.tradingview.com/news/reuters.com,2026:newsml_L6N41I0Y3:0-concentrated-us-markets-push-global-diversification-back-into-focus-nuveen/"
    },
    {
      "title": "Tuesday data downpour: JOLTS, services PMI, trade balance, new home sales",
      "source": "reuters",
      "color": "#ff6d00",
      "timestamp": "2026-05-05T16:35:09+00:00",
      "timeDisplay": "4:35 PM",
      "link": "https://www.tradingview.com/news/reuters.com,2026:newsml_L6N41I0XM:0-tuesday-data-downpour-jolts-services-pmi-trade-balance-new-home-sales/"
    },
    {
      "title": "US ATLANTA FED GDPNOW MODEL ESTIMATES US Q2 GDP GROWTH RATE AT 3.7%, UP FROM 3.5% LAST WEEK, AFTER LATEST ECONOMIC REPORTS",
      "source": "macenews",
      "color": "#00e5ff",
      "timestamp": "2026-05-05T16:13:00+00:00",
      "timeDisplay": "4:13 PM",
      "link": "https://www.tradingview.com/news/macenews:324ba022b094b:0-us-atlanta-fed-gdpnow-model-estimates-us-q2-gdp-growth-rate-at-3-7-up-from-3-5-last-week-after-latest-economic-reports/"
    },
    {
      "title": "Individual investors trim stocks, boost cash as sentiment sours - AAII",
      "source": "reuters",
      "color": "#ff6d00",
      "timestamp": "2026-05-05T16:06:42+00:00",
      "timeDisplay": "4:06 PM",
      "link": "https://www.tradingview.com/news/reuters.com,2026:newsml_L6N41I0WC:0-individual-investors-trim-stocks-boost-cash-as-sentiment-sours-aaii/"
    },
    {
      "title": "The 15% Ethereum Rally Hides a Network Problem That Just Reached Exchanges",
      "source": "beincrypto",
      "color": "#00e5ff",
      "timestamp": "2026-05-05T16:00:00+00:00",
      "timeDisplay": "4:00 PM",
      "link": "https://www.tradingview.com/news/beincrypto:0501165df094b:0-the-15-ethereum-rally-hides-a-network-problem-that-just-reached-exchanges/"
    }
  ]
}