{
  "lastUpdated": "2026-06-02T11:55:32.621801+00:00",
  "lastUpdatedDisplay": "Jun 02, 2026 \u2014 11:55 AM UTC",
  "articleCount": 75,
  "currentRegime": "Reflation",
  "currentRegimeColor": "#00e5ff",
  "regimeConfidence": "MEDIUM",
  "regimeAsOf": "2026-05-01T15:30:00-05:00",
  "summary": {
    "macroSummary": "Markets show cautious optimism as Middle East diplomatic efforts continue and oil prices decline, easing inflation concerns and reducing rate hike fears. Treasury yields are falling and the dollar remains range-bound, while Bitcoin faces significant pressure from Strategy's rare sale and Mt. Gox movements, dropping below $70K with $800M in crypto liquidations.",
    "regimePressure": "PRESSURING",
    "regimePressureReason": "Oil decline and easing Treasury yields directly contradict the stagflationary undertones of the Reflation regime, while diplomatic progress in Middle East reduces the embedded Iran-war oil shock assumption.",
    "thresholdWatches": [
      {
        "indicator": "Oil (WTI)",
        "level": "Dropping",
        "signal": "WTI crude oil drops as US-Iran uncertainty persists, moving away from $115 stagflation threshold"
      }
    ],
    "keySignals": [
      {
        "signal": "Oil prices declining as Middle East diplomacy progresses, reducing inflation pressure",
        "tag": "CONTRADICTS"
      },
      {
        "signal": "Treasury yields easing amid hopes for Mideast resolution, weakening stagflationary bond stress",
        "tag": "CONTRADICTS"
      },
      {
        "signal": "Gold rising on lower oil and easing rate hike fears, indicating disinflationary rather than reflationary forces",
        "tag": "CONTRADICTS"
      },
      {
        "signal": "Bitcoin drops below $70K on Strategy sale and Mt. Gox movements with $800M crypto liquidations",
        "tag": "NEUTRAL"
      },
      {
        "signal": "Dollar remains in tight range with no clear directional pressure toward DXY 100 threshold",
        "tag": "NEUTRAL"
      }
    ],
    "actionItems": [
      "Monitor oil prices for sustained decline below recent levels - contradicts embedded Iran-war shock assumption",
      "Watch Treasury yields for continued easing - undermines long-end stress component of regime thesis",
      "Consider BMNR ladder adjustments if crypto weakness persists amid broader disinflationary signals"
    ]
  },
  "articles": [
    {
      "title": "Gold climbs as lower oil eases inflation, rate-hike fears",
      "source": "reuters",
      "color": "#ff6d00",
      "timestamp": "2026-06-02T11:46:08+00:00",
      "timeDisplay": "11:46 AM",
      "link": "https://www.tradingview.com/news/reuters.com,2026:newsml_L1N42A0EE:0-gold-climbs-as-lower-oil-eases-inflation-rate-hike-fears/"
    },
    {
      "title": "Market Mood Improves As Middle East Diplomacy Stays",
      "source": "dpa_afx",
      "color": "#00e5ff",
      "timestamp": "2026-06-02T11:35:33+00:00",
      "timeDisplay": "11:35 AM",
      "link": "https://www.tradingview.com/news/dpa_afx:0ad74bac0f9ea:0-market-mood-improves-as-middle-east-diplomacy-stays/"
    },
    {
      "title": "Dollar Little Changed on Tuesday",
      "source": "trading-economics",
      "color": "#00e5ff",
      "timestamp": "2026-06-02T11:34:43+00:00",
      "timeDisplay": "11:34 AM",
      "link": "https://www.tradingview.com/news/te_news:555781:0-dollar-little-changed-on-tuesday/"
    },
    {
      "title": "Dollar in tight range as traders eye Middle East, US data",
      "source": "reuters",
      "color": "#ff6d00",
      "timestamp": "2026-06-02T11:34:35+00:00",
      "timeDisplay": "11:34 AM",
      "link": "https://www.tradingview.com/news/reuters.com,2026:newsml_L6N42A0M5:0-dollar-in-tight-range-as-traders-eye-middle-east-us-data/"
    },
    {
      "title": "Bitcoin Stays Weak on Geopolitical Uncertainty, Strategy's Sale of Cryptocurrency \u2014 Market Talk",
      "source": "dow-jones",
      "color": "#00e5ff",
      "timestamp": "2026-06-02T11:25:00+00:00",
      "timeDisplay": "11:25 AM",
      "link": "https://www.tradingview.com/news/DJN_DN20260602002603:0/"
    },
    {
      "title": "Gold rebounds Rs 1,050 on firm global cues; silver rises Rs 1,300",
      "source": "moneycontrol",
      "color": "#00e5ff",
      "timestamp": "2026-06-02T11:22:41+00:00",
      "timeDisplay": "11:22 AM",
      "link": "https://www.tradingview.com/news/moneycontrol:16e4991c9094b:0-gold-rebounds-rs-1-050-on-firm-global-cues-silver-rises-rs-1-300/"
    },
    {
      "title": "Strategy's About-Face on Bitcoin \u2014 WSJ",
      "source": "dow-jones",
      "color": "#00e5ff",
      "timestamp": "2026-06-02T11:14:00+00:00",
      "timeDisplay": "11:14 AM",
      "link": "https://www.tradingview.com/news/DJN_DN20260602002537:0/"
    },
    {
      "title": "Bitcoin back in \u2018distribution phase\u2019 as extreme fear grips crypto market",
      "source": "cointelegraph",
      "color": "#00e5ff",
      "timestamp": "2026-06-02T11:09:56+00:00",
      "timeDisplay": "11:09 AM",
      "link": "https://www.tradingview.com/news/cointelegraph:b930b3e59094b:0-bitcoin-back-in-distribution-phase-as-extreme-fear-grips-crypto-market/"
    },
    {
      "title": "Bitcoin falls to two-month low as Strategy sale, West Asia risks weigh",
      "source": "cnbctv",
      "color": "#00e5ff",
      "timestamp": "2026-06-02T11:08:52+00:00",
      "timeDisplay": "11:08 AM",
      "link": "https://www.tradingview.com/news/cnbctv:96ab5b6ad094b:0/"
    },
    {
      "title": "Crypto treasury inflows fall to lowest level since 2024",
      "source": "cointelegraph",
      "color": "#00e5ff",
      "timestamp": "2026-06-02T11:07:20+00:00",
      "timeDisplay": "11:07 AM",
      "link": "https://www.tradingview.com/news/cointelegraph:cd43931fe094b:0-crypto-treasury-inflows-fall-to-lowest-level-since-2024/"
    },
    {
      "title": "Strive Seeks $4.2 Billion ATM Expansion To Fund More Bitcoin Purchases",
      "source": "newsbtc",
      "color": "#00e5ff",
      "timestamp": "2026-06-02T11:00:42+00:00",
      "timeDisplay": "11:00 AM",
      "link": "https://www.tradingview.com/news/newsbtc:a82ecdd1f094b:0-strive-seeks-4-2-billion-atm-expansion-to-fund-more-bitcoin-purchases/"
    },
    {
      "title": "Treasury Yields Ease",
      "source": "trading-economics",
      "color": "#00e5ff",
      "timestamp": "2026-06-02T10:57:28+00:00",
      "timeDisplay": "10:57 AM",
      "link": "https://www.tradingview.com/news/te_news:555769:0-treasury-yields-ease/"
    },
    {
      "title": "Why Is Bitcoin Under $70K \u2013 Mt. Gox, Michael Saylor, And Iran Threat Pressure Markets",
      "source": "stocktwits",
      "color": "#00e5ff",
      "timestamp": "2026-06-02T10:44:14+00:00",
      "timeDisplay": "10:44 AM",
      "link": "https://www.tradingview.com/news/stocktwits:54cde328d094b:0-why-is-bitcoin-under-70k-mt-gox-michael-saylor-and-iran-threat-pressure-markets/"
    },
    {
      "title": "Vitalik Buterin proposes options-based synthetic assets to avoid liquidations and reduce reliance on real-time oracles",
      "source": "the_block",
      "color": "#00e5ff",
      "timestamp": "2026-06-02T10:31:02+00:00",
      "timeDisplay": "10:31 AM",
      "link": "https://www.tradingview.com/news/the_block:f0ae02b29094b:0-vitalik-buterin-proposes-options-based-synthetic-assets-to-avoid-liquidations-and-reduce-reliance-on-real-time-oracles/"
    },
    {
      "title": "U.S. Treasury Yields, Dollar Decline Amid Hopes for Mideast Resolution \u2014 Market Talk",
      "source": "dow-jones",
      "color": "#00e5ff",
      "timestamp": "2026-06-02T10:28:00+00:00",
      "timeDisplay": "10:28 AM",
      "link": "https://www.tradingview.com/news/DJN_DN20260602001842:0/"
    },
    {
      "title": "Ether Looks Set to Outperform Bitcoin \u2014 Market Talk",
      "source": "dow-jones",
      "color": "#00e5ff",
      "timestamp": "2026-06-02T10:27:00+00:00",
      "timeDisplay": "10:27 AM",
      "link": "https://www.tradingview.com/news/DJN_DN20260602001834:0/"
    },
    {
      "title": "Polymarket faces backlash over disputed Strategy bitcoin sale market",
      "source": "the_block",
      "color": "#00e5ff",
      "timestamp": "2026-06-02T10:14:29+00:00",
      "timeDisplay": "10:14 AM",
      "link": "https://www.tradingview.com/news/the_block:2ccfafcd2094b:0-polymarket-faces-backlash-over-disputed-strategy-bitcoin-sale-market/"
    },
    {
      "title": "Hyperscale Data Bitcoin Treasury Reaches Approximately 704.3405 Bitcoin",
      "source": "reuters",
      "color": "#ff6d00",
      "timestamp": "2026-06-02T10:11:39+00:00",
      "timeDisplay": "10:11 AM",
      "link": "https://www.tradingview.com/news/reuters.com,2026:newsml_FWN42A06I:0-hyperscale-data-bitcoin-treasury-reaches-approximately-704-3405-bitcoin/"
    },
    {
      "title": "Central bank hand contains rupee's fall, shrinks dollar-rupee forward premiums",
      "source": "reuters",
      "color": "#ff6d00",
      "timestamp": "2026-06-02T10:09:54+00:00",
      "timeDisplay": "10:09 AM",
      "link": "https://www.tradingview.com/news/reuters.com,2026:newsml_L4N42A0OW:0-central-bank-hand-contains-rupee-s-fall-shrinks-dollar-rupee-forward-premiums/"
    },
    {
      "title": "What does Mt. Gox's latest Bitcoin transfer mean for BTC price?",
      "source": "invezz",
      "color": "#00e5ff",
      "timestamp": "2026-06-02T09:46:03+00:00",
      "timeDisplay": "9:46 AM",
      "link": "https://www.tradingview.com/news/invezz:cf763cf12094b:0-what-does-mt-gox-s-latest-bitcoin-transfer-mean-for-btc-price/"
    },
    {
      "title": "Mt. Gox moves $739M in Bitcoin from cold wallets: Arkham",
      "source": "cointelegraph",
      "color": "#00e5ff",
      "timestamp": "2026-06-02T09:35:48+00:00",
      "timeDisplay": "9:35 AM",
      "link": "https://www.tradingview.com/news/cointelegraph:22f58f8e9094b:0-mt-gox-moves-739m-in-bitcoin-from-cold-wallets-arkham/"
    },
    {
      "title": "The Bitcoin Retracement Rally And The Resistance Level That Could End It All",
      "source": "newsbtc",
      "color": "#00e5ff",
      "timestamp": "2026-06-02T09:30:12+00:00",
      "timeDisplay": "9:30 AM",
      "link": "https://www.tradingview.com/news/newsbtc:b30ef5a64094b:0-the-bitcoin-retracement-rally-and-the-resistance-level-that-could-end-it-all/"
    },
    {
      "title": "Bitcoin Drops Below $70K: Analyst Says Strategy \u2018Slayed The Sacred Cow\u2019 With Rare BTC Sale",
      "source": "stocktwits",
      "color": "#00e5ff",
      "timestamp": "2026-06-02T09:20:33+00:00",
      "timeDisplay": "9:20 AM",
      "link": "https://www.tradingview.com/news/stocktwits:d4304771a094b:0-bitcoin-drops-below-70k-analyst-says-strategy-slayed-the-sacred-cow-with-rare-btc-sale/"
    },
    {
      "title": "Gold rises as lower oil eases inflation, rate-hike fears",
      "source": "reuters",
      "color": "#ff6d00",
      "timestamp": "2026-06-02T09:16:21+00:00",
      "timeDisplay": "9:16 AM",
      "link": "https://www.tradingview.com/news/reuters.com,2026:newsml_L1N42A09I:0-gold-rises-as-lower-oil-eases-inflation-rate-hike-fears/"
    },
    {
      "title": "CME\u2019s 24/7 crypto derivatives market sees $50 million in opening weekend trading",
      "source": "the_block",
      "color": "#00e5ff",
      "timestamp": "2026-06-02T09:06:26+00:00",
      "timeDisplay": "9:06 AM",
      "link": "https://www.tradingview.com/news/the_block:028acbb02094b:0-cme-s-24-7-crypto-derivatives-market-sees-50-million-in-opening-weekend-trading/"
    },
    {
      "title": "Crypto News Today (June 2): $766M in Liquidations as BTC Crashes Below $70K",
      "source": "99Bitcoins",
      "color": "#00e5ff",
      "timestamp": "2026-06-02T09:02:30+00:00",
      "timeDisplay": "9:02 AM",
      "link": "https://www.tradingview.com/news/99Bitcoins:b59b47155094b:0-crypto-news-today-june-2-766m-in-liquidations-as-btc-crashes-below-70k/"
    },
    {
      "title": "Orbs Advances V5 Upgrade for Agentic AI Crypto Trading Infrastructure",
      "source": "chainwire",
      "color": "#00e5ff",
      "timestamp": "2026-06-02T09:00:02+00:00",
      "timeDisplay": "9:00 AM",
      "link": "https://www.tradingview.com/news/chainwire:911503daf094b:0-orbs-advances-v5-upgrade-for-agentic-ai-crypto-trading-infrastructure/"
    },
    {
      "title": "Bitcoin price falls under $70K as crypto markets liquidate $800M",
      "source": "cointelegraph",
      "color": "#00e5ff",
      "timestamp": "2026-06-02T08:55:20+00:00",
      "timeDisplay": "8:55 AM",
      "link": "https://www.tradingview.com/news/cointelegraph:e1cde4099094b:0-bitcoin-price-falls-under-70k-as-crypto-markets-liquidate-800m/"
    },
    {
      "title": "WTI Crude Oil Drops as US-Iran Uncertainty Persists",
      "source": "trading-economics",
      "color": "#00e5ff",
      "timestamp": "2026-06-02T08:52:13+00:00",
      "timeDisplay": "8:52 AM",
      "link": "https://www.tradingview.com/news/te_news:555721:0-wti-crude-oil-drops-as-us-iran-uncertainty-persists/"
    },
    {
      "title": "Dollar Could Stick to Tight Range in Near Term \u2014 Market Talk",
      "source": "dow-jones",
      "color": "#00e5ff",
      "timestamp": "2026-06-02T08:46:00+00:00",
      "timeDisplay": "8:46 AM",
      "link": "https://www.tradingview.com/news/DJN_DN20260602001219:0/"
    },
    {
      "title": "Why Did Bitcoin Drop Below $70,000? Two Names Explain It",
      "source": "beincrypto",
      "color": "#00e5ff",
      "timestamp": "2026-06-02T08:41:48+00:00",
      "timeDisplay": "8:41 AM",
      "link": "https://www.tradingview.com/news/beincrypto:edce41855094b:0-why-did-bitcoin-drop-below-70-000-two-names-explain-it/"
    },
    {
      "title": "Global markets turn cautious amid Middle East tensions",
      "source": "invezz",
      "color": "#00e5ff",
      "timestamp": "2026-06-02T08:33:15+00:00",
      "timeDisplay": "8:33 AM",
      "link": "https://www.tradingview.com/news/invezz:02539e0af094b:0-global-markets-turn-cautious-amid-middle-east-tensions/"
    },
    {
      "title": "Gold gains on easing Treasury yields amid Mideast uncertainty",
      "source": "reuters",
      "color": "#ff6d00",
      "timestamp": "2026-06-02T07:57:20+00:00",
      "timeDisplay": "7:57 AM",
      "link": "https://www.tradingview.com/news/reuters.com,2026:newsml_L1N42A08B:0-gold-gains-on-easing-treasury-yields-amid-mideast-uncertainty/"
    },
    {
      "title": "Dollar stuck in narrow band as traders eye Middle East, US data",
      "source": "reuters",
      "color": "#ff6d00",
      "timestamp": "2026-06-02T07:56:11+00:00",
      "timeDisplay": "7:56 AM",
      "link": "https://www.tradingview.com/news/reuters.com,2026:newsml_L6N42A0CD:0-dollar-stuck-in-narrow-band-as-traders-eye-middle-east-us-data/"
    },
    {
      "title": "Gold Rises But Middle East Uncertainty Weighs on Outlook \u2014 Market Talk",
      "source": "dow-jones",
      "color": "#00e5ff",
      "timestamp": "2026-06-02T07:46:00+00:00",
      "timeDisplay": "7:46 AM",
      "link": "https://www.tradingview.com/news/DJN_DN20260602000937:0/"
    },
    {
      "title": "Why Is Bitcoin Price Down Today?\u00a0",
      "source": "coinpedia",
      "color": "#00e5ff",
      "timestamp": "2026-06-02T07:44:29+00:00",
      "timeDisplay": "7:44 AM",
      "link": "https://www.tradingview.com/news/coinpedia:3fdad5631094b:0-why-is-bitcoin-price-down-today/"
    },
    {
      "title": "Ethereum defends $1900 as BitMine slows buying and ETF outflows grow",
      "source": "invezz",
      "color": "#00e5ff",
      "timestamp": "2026-06-02T07:42:59+00:00",
      "timeDisplay": "7:42 AM",
      "link": "https://www.tradingview.com/news/invezz:4c5e440a2094b:0-ethereum-defends-1900-as-bitmine-slows-buying-and-etf-outflows-grow/"
    },
    {
      "title": "Oil Falls as Traders Weigh Mixed Messages Over U.S.-Iran Talks \u2014 Market Talk",
      "source": "dow-jones",
      "color": "#00e5ff",
      "timestamp": "2026-06-02T07:25:00+00:00",
      "timeDisplay": "7:25 AM",
      "link": "https://www.tradingview.com/news/DJN_DN20260602000866:0/"
    },
    {
      "title": "Eurozone Bond Yields Fall as Oil Prices Move Lower \u2014 Market Talk",
      "source": "dow-jones",
      "color": "#00e5ff",
      "timestamp": "2026-06-02T07:22:00+00:00",
      "timeDisplay": "7:22 AM",
      "link": "https://www.tradingview.com/news/DJN_DN20260602000853:0/"
    },
    {
      "title": "Bitcoin crashes below $70K as Iran tensions and ETF outflows bite",
      "source": "invezz",
      "color": "#00e5ff",
      "timestamp": "2026-06-02T07:20:19+00:00",
      "timeDisplay": "7:20 AM",
      "link": "https://www.tradingview.com/news/invezz:523d60ec1094b:0-bitcoin-crashes-below-70k-as-iran-tensions-and-etf-outflows-bite/"
    },
    {
      "title": "Dollar index edges lower as traders focus on US labour market signals",
      "source": "invezz",
      "color": "#00e5ff",
      "timestamp": "2026-06-02T07:03:34+00:00",
      "timeDisplay": "7:03 AM",
      "link": "https://www.tradingview.com/news/invezz:c909bc54f094b:0-dollar-index-edges-lower-as-traders-focus-on-us-labour-market-signals/"
    },
    {
      "title": "Oil Slips as US-Iran Uncertainty Persists",
      "source": "trading-economics",
      "color": "#00e5ff",
      "timestamp": "2026-06-02T07:02:32+00:00",
      "timeDisplay": "7:02 AM",
      "link": "https://www.tradingview.com/news/te_news:555649:0-oil-slips-as-us-iran-uncertainty-persists/"
    },
    {
      "title": "Dollar Eases After Partial Ceasefire Between Hezbollah and Israel \u2014 Market Talk",
      "source": "dow-jones",
      "color": "#00e5ff",
      "timestamp": "2026-06-02T06:50:00+00:00",
      "timeDisplay": "6:50 AM",
      "link": "https://www.tradingview.com/news/DJN_DN20260602000694:0/"
    },
    {
      "title": "Gold Rebounds as Oil Prices Ease",
      "source": "trading-economics",
      "color": "#00e5ff",
      "timestamp": "2026-06-02T06:36:32+00:00",
      "timeDisplay": "6:36 AM",
      "link": "https://www.tradingview.com/news/te_news:555634:0-gold-rebounds-as-oil-prices-ease/"
    },
    {
      "title": "Ethtry Purchases 108.33 Ethereum As Part Of Treasury Strategy",
      "source": "reuters",
      "color": "#ff6d00",
      "timestamp": "2026-06-02T06:33:33+00:00",
      "timeDisplay": "6:33 AM",
      "link": "https://www.tradingview.com/news/reuters.com,2026:newsml_FWN42A00P:0-ethtry-purchases-108-33-ethereum-as-part-of-treasury-strategy/"
    },
    {
      "title": "A Whale Just Opened a $44 Million ETH Short: Why Hyperliquid Traders Are Moving Against It",
      "source": "beincrypto",
      "color": "#00e5ff",
      "timestamp": "2026-06-02T06:00:44+00:00",
      "timeDisplay": "6:00 AM",
      "link": "https://www.tradingview.com/news/beincrypto:fb0539adb094b:0-a-whale-just-opened-a-44-million-eth-short-why-hyperliquid-traders-are-moving-against-it/"
    },
    {
      "title": "Crypto Crash Alert: Why Tom Lee Remains Bullish For Bitcoin and Ethereum",
      "source": "coinpedia",
      "color": "#00e5ff",
      "timestamp": "2026-06-02T05:13:25+00:00",
      "timeDisplay": "5:13 AM",
      "link": "https://www.tradingview.com/news/coinpedia:4f993f3b7094b:0-crypto-crash-alert-why-tom-lee-remains-bullish-for-bitcoin-and-ethereum/"
    },
    {
      "title": "Gold edges higher on easing Treasury yields amid Mideast uncertainty",
      "source": "reuters",
      "color": "#ff6d00",
      "timestamp": "2026-06-02T04:41:02+00:00",
      "timeDisplay": "4:41 AM",
      "link": "https://www.tradingview.com/news/reuters.com,2026:newsml_L1N42A04M:0-gold-edges-higher-on-easing-treasury-yields-amid-mideast-uncertainty/"
    },
    {
      "title": "Dollar steady as traders await progress on Middle East peace talks",
      "source": "reuters",
      "color": "#ff6d00",
      "timestamp": "2026-06-02T04:33:11+00:00",
      "timeDisplay": "4:33 AM",
      "link": "https://www.tradingview.com/news/reuters.com,2026:newsml_L1N42A03W:0-dollar-steady-as-traders-await-progress-on-middle-east-peace-talks/"
    },
    {
      "title": "Bitmine buys $52M ETH as Tom Lee says price not yet showing Ethereum\u2019s strength",
      "source": "cointelegraph",
      "color": "#00e5ff",
      "timestamp": "2026-06-02T04:03:00+00:00",
      "timeDisplay": "4:03 AM",
      "link": "https://www.tradingview.com/news/cointelegraph:becd96a8f094b:0-bitmine-buys-52m-eth-as-tom-lee-says-price-not-yet-showing-ethereum-s-strength/"
    },
    {
      "title": "China's yuan hits 3-year high; investors eye Mideast peace talks",
      "source": "reuters",
      "color": "#ff6d00",
      "timestamp": "2026-06-02T03:45:19+00:00",
      "timeDisplay": "3:45 AM",
      "link": "https://www.tradingview.com/news/reuters.com,2026:newsml_L1N42A04A:0-china-s-yuan-hits-3-year-high-investors-eye-mideast-peace-talks/"
    },
    {
      "title": "Oil swings keep rupee outlook precarious, foreign stock sales amplify strain",
      "source": "reuters",
      "color": "#ff6d00",
      "timestamp": "2026-06-02T02:59:05+00:00",
      "timeDisplay": "2:59 AM",
      "link": "https://www.tradingview.com/news/reuters.com,2026:newsml_L1N42A03A:0-oil-swings-keep-rupee-outlook-precarious-foreign-stock-sales-amplify-strain/"
    },
    {
      "title": "Gold steady amid uncertainty over US-Iran peace negotiations",
      "source": "reuters",
      "color": "#ff6d00",
      "timestamp": "2026-06-02T02:47:38+00:00",
      "timeDisplay": "2:47 AM",
      "link": "https://www.tradingview.com/news/reuters.com,2026:newsml_L1N42A02A:0-gold-steady-amid-uncertainty-over-us-iran-peace-negotiations/"
    },
    {
      "title": "US 10-Year Yield Steadies After Volatile Session",
      "source": "trading-economics",
      "color": "#00e5ff",
      "timestamp": "2026-06-02T02:28:40+00:00",
      "timeDisplay": "2:28 AM",
      "link": "https://www.tradingview.com/news/te_news:555556:0-us-10-year-yield-steadies-after-volatile-session/"
    },
    {
      "title": "Ethereum Price $2,000 Floor Gives Way As Selling Pressure Persists",
      "source": "newsbtc",
      "color": "#00e5ff",
      "timestamp": "2026-06-02T02:28:37+00:00",
      "timeDisplay": "2:28 AM",
      "link": "https://www.tradingview.com/news/newsbtc:76d5f948b094b:0-ethereum-price-2-000-floor-gives-way-as-selling-pressure-persists/"
    },
    {
      "title": "Commodities intraday targets/key levels",
      "source": "reuters",
      "color": "#ff6d00",
      "timestamp": "2026-06-02T01:45:02+00:00",
      "timeDisplay": "1:45 AM",
      "link": "https://www.tradingview.com/news/reuters.com,2026:newsml_L1N42A01Z:0-commodities-intraday-targets-key-levels/"
    },
    {
      "title": "TUESDAY WHITE HOUSE SCHEDULE - Subject to additions during the day",
      "source": "macenews",
      "color": "#00e5ff",
      "timestamp": "2026-06-02T01:26:00+00:00",
      "timeDisplay": "1:26 AM",
      "link": "https://www.tradingview.com/news/macenews:1c7e1ebfa094b:0-tuesday-white-house-schedule-subject-to-additions-during-the-day/"
    },
    {
      "title": "Gold holds decline as traders weigh confusion over US-Iran talks",
      "source": "moneycontrol",
      "color": "#00e5ff",
      "timestamp": "2026-06-02T01:25:37+00:00",
      "timeDisplay": "1:25 AM",
      "link": "https://www.tradingview.com/news/moneycontrol:e2895f76c094b:0-gold-holds-decline-as-traders-weigh-confusion-over-us-iran-talks/"
    },
    {
      "title": "Dollar Holds Gains Amid US-Iran Impasse",
      "source": "trading-economics",
      "color": "#00e5ff",
      "timestamp": "2026-06-02T01:15:39+00:00",
      "timeDisplay": "1:15 AM",
      "link": "https://www.tradingview.com/news/te_news:555519:0-dollar-holds-gains-amid-us-iran-impasse/"
    },
    {
      "title": "Gold Edges Lower; Investors Focus on Energy-Driven Inflation \u2014 Market Talk",
      "source": "dow-jones",
      "color": "#00e5ff",
      "timestamp": "2026-06-02T01:12:00+00:00",
      "timeDisplay": "1:12 AM",
      "link": "https://www.tradingview.com/news/DJN_DN20260601010098:0/"
    },
    {
      "title": "Gold Appears Trapped Between Two Powerful Narratives \u2014 Market Talk",
      "source": "dow-jones",
      "color": "#00e5ff",
      "timestamp": "2026-06-02T00:10:00+00:00",
      "timeDisplay": "12:10 AM",
      "link": "https://www.tradingview.com/news/DJN_DN20260601009975:0/"
    },
    {
      "title": "Gold Holds Losses on Inflation Worries",
      "source": "trading-economics",
      "color": "#00e5ff",
      "timestamp": "2026-06-01T23:49:05+00:00",
      "timeDisplay": "11:49 PM",
      "link": "https://www.tradingview.com/news/te_news:555499:0-gold-holds-losses-on-inflation-worries/"
    },
    {
      "title": "Oil Edges Higher; Trump Seeks to Quell Israel-Hezbollah Conflict \u2014 Market Talk",
      "source": "dow-jones",
      "color": "#00e5ff",
      "timestamp": "2026-06-01T23:37:00+00:00",
      "timeDisplay": "11:37 PM",
      "link": "https://www.tradingview.com/news/DJN_DN20260601009898:0/"
    },
    {
      "title": "Oil Holds Gains on US-Iran Stalemate",
      "source": "trading-economics",
      "color": "#00e5ff",
      "timestamp": "2026-06-01T23:35:33+00:00",
      "timeDisplay": "11:35 PM",
      "link": "https://www.tradingview.com/news/te_news:555497:0-oil-holds-gains-on-us-iran-stalemate/"
    },
    {
      "title": "Was Bankless Founder Right to Sell His Ethereum? On-Chain Data Reveals",
      "source": "beincrypto",
      "color": "#00e5ff",
      "timestamp": "2026-06-01T23:30:00+00:00",
      "timeDisplay": "11:30 PM",
      "link": "https://www.tradingview.com/news/beincrypto:b169a0029094b:0-was-bankless-founder-right-to-sell-his-ethereum-on-chain-data-reveals/"
    },
    {
      "title": "U.S. Dollar Advances As Strait Of Hormuz Continues To Remain Shut",
      "source": "dpa_afx",
      "color": "#00e5ff",
      "timestamp": "2026-06-01T21:14:52+00:00",
      "timeDisplay": "9:14 PM",
      "link": "https://www.tradingview.com/news/dpa_afx:87556f7aeff3c:0-u-s-dollar-advances-as-strait-of-hormuz-continues-to-remain-shut/"
    },
    {
      "title": "Oil Prices Pare Some Gains But Remain Elevated",
      "source": "trading-economics",
      "color": "#00e5ff",
      "timestamp": "2026-06-01T20:10:19+00:00",
      "timeDisplay": "8:10 PM",
      "link": "https://www.tradingview.com/news/te_news:555475:0-oil-prices-pare-some-gains-but-remain-elevated/"
    },
    {
      "title": "Dollar Rises on Hawkish Rally in Oil Prices",
      "source": "barchart",
      "color": "#00e5ff",
      "timestamp": "2026-06-01T19:50:43+00:00",
      "timeDisplay": "7:50 PM",
      "link": "https://www.tradingview.com/news/barchart:2f896efc1094b:0-dollar-rises-on-hawkish-rally-in-oil-prices/"
    },
    {
      "title": "Dollar higher as markets parse fragile Middle East peace talks",
      "source": "reuters",
      "color": "#ff6d00",
      "timestamp": "2026-06-01T19:50:43+00:00",
      "timeDisplay": "7:50 PM",
      "link": "https://www.tradingview.com/news/reuters.com,2026:newsml_L1N4290N5:0-dollar-higher-as-markets-parse-fragile-middle-east-peace-talks/"
    },
    {
      "title": "US yields higher as uncertainty surrounds Iran talks",
      "source": "reuters",
      "color": "#ff6d00",
      "timestamp": "2026-06-01T19:35:13+00:00",
      "timeDisplay": "7:35 PM",
      "link": "https://www.tradingview.com/news/reuters.com,2026:newsml_L6N429147:0-us-yields-higher-as-uncertainty-surrounds-iran-talks/"
    },
    {
      "title": "Unable to recover from roughly $50 million hack, Radiant Capital is winding down",
      "source": "the_block",
      "color": "#00e5ff",
      "timestamp": "2026-06-01T19:33:31+00:00",
      "timeDisplay": "7:33 PM",
      "link": "https://www.tradingview.com/news/the_block:ccbcd209e094b:0-unable-to-recover-from-roughly-50-million-hack-radiant-capital-is-winding-down/"
    },
    {
      "title": "US ISM Manufacturing PMI Expands for 5th Straight Month in May, Backed by New Orders, but Mideast Conflict Keeping Costs High",
      "source": "macenews",
      "color": "#00e5ff",
      "timestamp": "2026-06-01T19:04:00+00:00",
      "timeDisplay": "7:04 PM",
      "link": "https://www.tradingview.com/news/macenews:11e2eade5094b:0-us-ism-manufacturing-pmi-expands-for-5th-straight-month-in-may-backed-by-new-orders-but-mideast-conflict-keeping-costs-high/"
    },
    {
      "title": "Oil Prices Soar as Iran Halts US-Iran Ceasefire Negotiations",
      "source": "barchart",
      "color": "#00e5ff",
      "timestamp": "2026-06-01T19:02:25+00:00",
      "timeDisplay": "7:02 PM",
      "link": "https://www.tradingview.com/news/barchart:f4f033fb2094b:0-oil-prices-soar-as-iran-halts-us-iran-ceasefire-negotiations/"
    },
    {
      "title": "Oil Futures Rise On Concerns About U.S.-Iran Talks \u2014 Market Talk",
      "source": "dow-jones",
      "color": "#00e5ff",
      "timestamp": "2026-06-01T19:01:00+00:00",
      "timeDisplay": "7:01 PM",
      "link": "https://www.tradingview.com/news/DJN_DN20260601007383:0/"
    },
    {
      "title": "Gold falls with inflation worries rising on Middle East conflict",
      "source": "reuters",
      "color": "#ff6d00",
      "timestamp": "2026-06-01T18:15:33+00:00",
      "timeDisplay": "6:15 PM",
      "link": "https://www.tradingview.com/news/reuters.com,2026:newsml_L1N4290SP:0-gold-falls-with-inflation-worries-rising-on-middle-east-conflict/"
    }
  ]
}