{
  "lastUpdated": "2026-06-02T02:08:29.068201+00:00",
  "lastUpdatedDisplay": "Jun 02, 2026 \u2014 02:08 AM UTC",
  "articleCount": 75,
  "currentRegime": "Reflation",
  "currentRegimeColor": "#00e5ff",
  "regimeConfidence": "MEDIUM",
  "regimeAsOf": "2026-05-01T15:30:00-05:00",
  "summary": {
    "macroSummary": "Markets are navigating stalled US-Iran peace talks with the Strait of Hormuz remaining shut, keeping oil elevated and inflation concerns rising. MicroStrategy's first Bitcoin sale since 2022 has pressured crypto markets, while gold declines on inflation worries and dollar strength persists amid Middle East uncertainty.",
    "regimePressure": "REINFORCING",
    "regimePressureReason": "Headlines reinforce the Reflation regime with sustained geopolitical oil supply disruption (Strait of Hormuz shut), rising inflation concerns, and dollar strength - all consistent with the Iran-war oil shock and stagflationary undertones identified in the current regime.",
    "thresholdWatches": [],
    "keySignals": [
      {
        "signal": "Strait of Hormuz remains shut with stalled US-Iran talks, sustaining oil supply disruption and inflation pressure",
        "tag": "SUPPORTS"
      },
      {
        "signal": "ISM Manufacturing expanded for 5th straight month but costs remain high due to Mideast conflict, confirming stagflationary mix",
        "tag": "SUPPORTS"
      },
      {
        "signal": "Dollar advancing and US yields rising amid Middle East uncertainty, supporting reflation dynamics",
        "tag": "SUPPORTS"
      },
      {
        "signal": "MicroStrategy's first Bitcoin sale since 2022 signals potential stress in risk assets and treasury management pressure",
        "tag": "NEUTRAL"
      },
      {
        "signal": "Gold declining on inflation worries rather than safe-haven demand, indicating markets pricing growth over flight-to-quality",
        "tag": "SUPPORTS"
      }
    ],
    "actionItems": [
      "Monitor oil prices closely as sustained elevation supports the Iran-war shock embedded in current regime",
      "Watch for any BMNR volatility spillover from broader crypto weakness following MicroStrategy sale",
      "Consider tightening stops on cyclical positions if dollar strength accelerates toward DXY 100 threshold"
    ]
  },
  "articles": [
    {
      "title": "Commodities intraday targets/key levels",
      "source": "reuters",
      "color": "#ff6d00",
      "timestamp": "2026-06-02T01:45:02+00:00",
      "timeDisplay": "1:45 AM",
      "link": "https://www.tradingview.com/news/reuters.com,2026:newsml_L1N42A01Z:0-commodities-intraday-targets-key-levels/"
    },
    {
      "title": "Chart of the Day: Ansem\u2019s thesis \u2014 alt season while Bitcoin \u201cchops itself to death\u201d",
      "source": "bravenewcoin",
      "color": "#00e5ff",
      "timestamp": "2026-06-02T01:38:05+00:00",
      "timeDisplay": "1:38 AM",
      "link": "https://www.tradingview.com/news/bravenewcoin:53303a3a8094b:0/"
    },
    {
      "title": "TUESDAY WHITE HOUSE SCHEDULE - Subject to additions during the day",
      "source": "macenews",
      "color": "#00e5ff",
      "timestamp": "2026-06-02T01:26:00+00:00",
      "timeDisplay": "1:26 AM",
      "link": "https://www.tradingview.com/news/macenews:1c7e1ebfa094b:0-tuesday-white-house-schedule-subject-to-additions-during-the-day/"
    },
    {
      "title": "Gold holds decline as traders weigh confusion over US-Iran talks",
      "source": "moneycontrol",
      "color": "#00e5ff",
      "timestamp": "2026-06-02T01:25:37+00:00",
      "timeDisplay": "1:25 AM",
      "link": "https://www.tradingview.com/news/moneycontrol:e2895f76c094b:0-gold-holds-decline-as-traders-weigh-confusion-over-us-iran-talks/"
    },
    {
      "title": "Bitcoin Price Cracks Lower, Opening The Door To More Pain",
      "source": "newsbtc",
      "color": "#00e5ff",
      "timestamp": "2026-06-02T01:22:04+00:00",
      "timeDisplay": "1:22 AM",
      "link": "https://www.tradingview.com/news/newsbtc:89dc4aedb094b:0-bitcoin-price-cracks-lower-opening-the-door-to-more-pain/"
    },
    {
      "title": "Dollar Holds Gains Amid US-Iran Impasse",
      "source": "trading-economics",
      "color": "#00e5ff",
      "timestamp": "2026-06-02T01:15:39+00:00",
      "timeDisplay": "1:15 AM",
      "link": "https://www.tradingview.com/news/te_news:555519:0-dollar-holds-gains-amid-us-iran-impasse/"
    },
    {
      "title": "Gold Edges Lower; Investors Focus on Energy-Driven Inflation \u2014 Market Talk",
      "source": "dow-jones",
      "color": "#00e5ff",
      "timestamp": "2026-06-02T01:12:00+00:00",
      "timeDisplay": "1:12 AM",
      "link": "https://www.tradingview.com/news/DJN_DN20260601010098:0/"
    },
    {
      "title": "Gold steady amid uncertainty over US-Iran peace negotiations",
      "source": "reuters",
      "color": "#ff6d00",
      "timestamp": "2026-06-02T01:10:15+00:00",
      "timeDisplay": "1:10 AM",
      "link": "https://www.tradingview.com/news/reuters.com,2026:newsml_L4N42A023:0-gold-steady-amid-uncertainty-over-us-iran-peace-negotiations/"
    },
    {
      "title": "Dollar steady as traders await progress on Middle East peace talks",
      "source": "reuters",
      "color": "#ff6d00",
      "timestamp": "2026-06-02T00:49:56+00:00",
      "timeDisplay": "12:49 AM",
      "link": "https://www.tradingview.com/news/reuters.com,2026:newsml_L4N4291RS:0-dollar-steady-as-traders-await-progress-on-middle-east-peace-talks/"
    },
    {
      "title": "Gold Appears Trapped Between Two Powerful Narratives \u2014 Market Talk",
      "source": "dow-jones",
      "color": "#00e5ff",
      "timestamp": "2026-06-02T00:10:00+00:00",
      "timeDisplay": "12:10 AM",
      "link": "https://www.tradingview.com/news/DJN_DN20260601009975:0/"
    },
    {
      "title": "Gold Holds Losses on Inflation Worries",
      "source": "trading-economics",
      "color": "#00e5ff",
      "timestamp": "2026-06-01T23:49:05+00:00",
      "timeDisplay": "11:49 PM",
      "link": "https://www.tradingview.com/news/te_news:555499:0-gold-holds-losses-on-inflation-worries/"
    },
    {
      "title": "Oil Edges Higher; Trump Seeks to Quell Israel-Hezbollah Conflict \u2014 Market Talk",
      "source": "dow-jones",
      "color": "#00e5ff",
      "timestamp": "2026-06-01T23:37:00+00:00",
      "timeDisplay": "11:37 PM",
      "link": "https://www.tradingview.com/news/DJN_DN20260601009898:0/"
    },
    {
      "title": "Oil Holds Gains on US-Iran Stalemate",
      "source": "trading-economics",
      "color": "#00e5ff",
      "timestamp": "2026-06-01T23:35:33+00:00",
      "timeDisplay": "11:35 PM",
      "link": "https://www.tradingview.com/news/te_news:555497:0-oil-holds-gains-on-us-iran-stalemate/"
    },
    {
      "title": "Was Bankless Founder Right to Sell His Ethereum? On-Chain Data Reveals",
      "source": "beincrypto",
      "color": "#00e5ff",
      "timestamp": "2026-06-01T23:30:00+00:00",
      "timeDisplay": "11:30 PM",
      "link": "https://www.tradingview.com/news/beincrypto:b169a0029094b:0-was-bankless-founder-right-to-sell-his-ethereum-on-chain-data-reveals/"
    },
    {
      "title": "Bitcoin bulls eye fresh positions after BTC price drops under $71K",
      "source": "cointelegraph",
      "color": "#00e5ff",
      "timestamp": "2026-06-01T22:54:07+00:00",
      "timeDisplay": "10:54 PM",
      "link": "https://www.tradingview.com/news/cointelegraph:68338f288094b:0-bitcoin-bulls-eye-fresh-positions-after-btc-price-drops-under-71k/"
    },
    {
      "title": "Polymarket Faces Backlash Over MicroStrategy Bitcoin Sale Dispute",
      "source": "beincrypto",
      "color": "#00e5ff",
      "timestamp": "2026-06-01T21:50:46+00:00",
      "timeDisplay": "9:50 PM",
      "link": "https://www.tradingview.com/news/beincrypto:86f6120db094b:0-polymarket-faces-backlash-over-microstrategy-bitcoin-sale-dispute/"
    },
    {
      "title": "Strategy Sells Bitcoin for First Time Since 2022. The Stock Is Sliding. \u2014 Barrons.com",
      "source": "dow-jones",
      "color": "#00e5ff",
      "timestamp": "2026-06-01T21:42:00+00:00",
      "timeDisplay": "9:42 PM",
      "link": "https://www.tradingview.com/news/DJN_DN20260601003612:0/"
    },
    {
      "title": "U.S. Dollar Advances As Strait Of Hormuz Continues To Remain Shut",
      "source": "dpa_afx",
      "color": "#00e5ff",
      "timestamp": "2026-06-01T21:14:52+00:00",
      "timeDisplay": "9:14 PM",
      "link": "https://www.tradingview.com/news/dpa_afx:87556f7aeff3c:0-u-s-dollar-advances-as-strait-of-hormuz-continues-to-remain-shut/"
    },
    {
      "title": "Saylor's Strategy Sells Bitcoin for First Time Since 2022 \u2014 WSJ",
      "source": "dow-jones",
      "color": "#00e5ff",
      "timestamp": "2026-06-01T21:06:00+00:00",
      "timeDisplay": "9:06 PM",
      "link": "https://www.tradingview.com/news/DJN_DN20260601007196:0/"
    },
    {
      "title": "Bitcoin volatility is down 56% but analysts still expect up to 20% BTC price move",
      "source": "cointelegraph",
      "color": "#00e5ff",
      "timestamp": "2026-06-01T20:34:46+00:00",
      "timeDisplay": "8:34 PM",
      "link": "https://www.tradingview.com/news/cointelegraph:fb1f1a602094b:0-bitcoin-volatility-is-down-56-but-analysts-still-expect-up-to-20-btc-price-move/"
    },
    {
      "title": "Bitcoin Is Still Following This Descending Channel Pattern And The Endgame Shows The Bottom",
      "source": "newsbtc",
      "color": "#00e5ff",
      "timestamp": "2026-06-01T20:30:33+00:00",
      "timeDisplay": "8:30 PM",
      "link": "https://www.tradingview.com/news/newsbtc:c567d82dd094b:0-bitcoin-is-still-following-this-descending-channel-pattern-and-the-endgame-shows-the-bottom/"
    },
    {
      "title": "Oil Prices Pare Some Gains But Remain Elevated",
      "source": "trading-economics",
      "color": "#00e5ff",
      "timestamp": "2026-06-01T20:10:19+00:00",
      "timeDisplay": "8:10 PM",
      "link": "https://www.tradingview.com/news/te_news:555475:0-oil-prices-pare-some-gains-but-remain-elevated/"
    },
    {
      "title": "Dollar higher as markets parse fragile Middle East peace talks",
      "source": "reuters",
      "color": "#ff6d00",
      "timestamp": "2026-06-01T19:50:43+00:00",
      "timeDisplay": "7:50 PM",
      "link": "https://www.tradingview.com/news/reuters.com,2026:newsml_L1N4290N5:0-dollar-higher-as-markets-parse-fragile-middle-east-peace-talks/"
    },
    {
      "title": "US yields higher as uncertainty surrounds Iran talks",
      "source": "reuters",
      "color": "#ff6d00",
      "timestamp": "2026-06-01T19:35:13+00:00",
      "timeDisplay": "7:35 PM",
      "link": "https://www.tradingview.com/news/reuters.com,2026:newsml_L6N429147:0-us-yields-higher-as-uncertainty-surrounds-iran-talks/"
    },
    {
      "title": "Unable to recover from roughly $50 million hack, Radiant Capital is winding down",
      "source": "the_block",
      "color": "#00e5ff",
      "timestamp": "2026-06-01T19:33:31+00:00",
      "timeDisplay": "7:33 PM",
      "link": "https://www.tradingview.com/news/the_block:ccbcd209e094b:0-unable-to-recover-from-roughly-50-million-hack-radiant-capital-is-winding-down/"
    },
    {
      "title": "US ISM Manufacturing PMI Expands for 5th Straight Month in May, Backed by New Orders, but Mideast Conflict Keeping Costs High",
      "source": "macenews",
      "color": "#00e5ff",
      "timestamp": "2026-06-01T19:04:00+00:00",
      "timeDisplay": "7:04 PM",
      "link": "https://www.tradingview.com/news/macenews:11e2eade5094b:0-us-ism-manufacturing-pmi-expands-for-5th-straight-month-in-may-backed-by-new-orders-but-mideast-conflict-keeping-costs-high/"
    },
    {
      "title": "Oil Futures Rise On Concerns About U.S.-Iran Talks \u2014 Market Talk",
      "source": "dow-jones",
      "color": "#00e5ff",
      "timestamp": "2026-06-01T19:01:00+00:00",
      "timeDisplay": "7:01 PM",
      "link": "https://www.tradingview.com/news/DJN_DN20260601007383:0/"
    },
    {
      "title": "Has Bitcoin Bottomed At $60,000 To Return To $100,000, Or Is This Just The Start Of Another Crash?",
      "source": "newsbtc",
      "color": "#00e5ff",
      "timestamp": "2026-06-01T19:00:59+00:00",
      "timeDisplay": "7:00 PM",
      "link": "https://www.tradingview.com/news/newsbtc:84a0c744b094b:0-has-bitcoin-bottomed-at-60-000-to-return-to-100-000-or-is-this-just-the-start-of-another-crash/"
    },
    {
      "title": "Strategy's BTC sale turns Bitcoin treasury into market stress test",
      "source": "cointelegraph",
      "color": "#00e5ff",
      "timestamp": "2026-06-01T18:25:00+00:00",
      "timeDisplay": "6:25 PM",
      "link": "https://www.tradingview.com/news/cointelegraph:3d089ac82094b:0-strategy-s-btc-sale-turns-bitcoin-treasury-into-market-stress-test/"
    },
    {
      "title": "Gold falls with inflation worries rising on Middle East conflict",
      "source": "reuters",
      "color": "#ff6d00",
      "timestamp": "2026-06-01T18:15:33+00:00",
      "timeDisplay": "6:15 PM",
      "link": "https://www.tradingview.com/news/reuters.com,2026:newsml_L1N4290SP:0-gold-falls-with-inflation-worries-rising-on-middle-east-conflict/"
    },
    {
      "title": "Strategy Sells Bitcoin for First Time Since 2022 as Shares Drop 6%",
      "source": "gurufocus",
      "color": "#00e5ff",
      "timestamp": "2026-06-01T18:05:37+00:00",
      "timeDisplay": "6:05 PM",
      "link": "https://www.tradingview.com/news/gurufocus:43a22ffad094b:0-strategy-sells-bitcoin-for-first-time-since-2022-as-shares-drop-6/"
    },
    {
      "title": "Bitcoin Outlook Hinges On A Handful Of Critical Price Zones",
      "source": "newsbtc",
      "color": "#00e5ff",
      "timestamp": "2026-06-01T17:30:54+00:00",
      "timeDisplay": "5:30 PM",
      "link": "https://www.tradingview.com/news/newsbtc:fc7a7aa38094b:0-bitcoin-outlook-hinges-on-a-handful-of-critical-price-zones/"
    },
    {
      "title": "Strategy Sells Bitcoin for First Time Since 2022 to Fund Dividends",
      "source": "gurufocus",
      "color": "#00e5ff",
      "timestamp": "2026-06-01T17:23:22+00:00",
      "timeDisplay": "5:23 PM",
      "link": "https://www.tradingview.com/news/gurufocus:9d0a4ab81094b:0-strategy-sells-bitcoin-for-first-time-since-2022-to-fund-dividends/"
    },
    {
      "title": "Bitcoin 'Rage Quitting' Sends It Slumping. Where Does It Go From Here? \u2014 Barrons.com",
      "source": "dow-jones",
      "color": "#00e5ff",
      "timestamp": "2026-06-01T17:19:00+00:00",
      "timeDisplay": "5:19 PM",
      "link": "https://www.tradingview.com/news/DJN_DN20260601006913:0/"
    },
    {
      "title": "Stronger fundamentals set this market apart from the dot-com bubble \u00a0",
      "source": "reuters",
      "color": "#ff6d00",
      "timestamp": "2026-06-01T17:11:10+00:00",
      "timeDisplay": "5:11 PM",
      "link": "https://www.tradingview.com/news/reuters.com,2026:newsml_L6N42910P:0-stronger-fundamentals-set-this-market-apart-from-the-dot-com-bubble/"
    },
    {
      "title": "Correction to Hyperliquid Market Talk",
      "source": "dow-jones",
      "color": "#00e5ff",
      "timestamp": "2026-06-01T16:54:00+00:00",
      "timeDisplay": "4:54 PM",
      "link": "https://www.tradingview.com/news/DJN_DN20260601006747:0/"
    },
    {
      "title": "Why are Bitcoin, Ethereum and XRP Prices Crashing Today?",
      "source": "coinpedia",
      "color": "#00e5ff",
      "timestamp": "2026-06-01T16:50:34+00:00",
      "timeDisplay": "4:50 PM",
      "link": "https://www.tradingview.com/news/coinpedia:e16849433094b:0-why-are-bitcoin-ethereum-and-xrp-prices-crashing-today/"
    },
    {
      "title": "Strategy bitcoin sale timing throws wrench into $20 million Polymarket pool",
      "source": "the_block",
      "color": "#00e5ff",
      "timestamp": "2026-06-01T16:40:18+00:00",
      "timeDisplay": "4:40 PM",
      "link": "https://www.tradingview.com/news/the_block:6cea84bc2094b:0-strategy-bitcoin-sale-timing-throws-wrench-into-20-million-polymarket-pool/"
    },
    {
      "title": "Strategy's stock drops after rare bitcoin sale tests 'never sell' narrative",
      "source": "market-watch",
      "color": "#00e5ff",
      "timestamp": "2026-06-01T16:31:00+00:00",
      "timeDisplay": "4:31 PM",
      "link": "https://www.tradingview.com/news/DJN_SN20260601008884:0/"
    },
    {
      "title": "IRAN UPDATE: CONFUSION AS UNCONFIRMED RPT IRAN BREAKS OFF TRUCE TALKS BECAUSE OF ISRAEL ATTACKS ON HEZBOLLAH; ISRAEL ESCALATES ATTACKS; TRUMP: 'RELAX'",
      "source": "macenews",
      "color": "#00e5ff",
      "timestamp": "2026-06-01T16:21:00+00:00",
      "timeDisplay": "4:21 PM",
      "link": "https://www.tradingview.com/news/macenews:6372ccb95094b:0-iran-update-confusion-as-unconfirmed-rpt-iran-breaks-off-truce-talks-because-of-israel-attacks-on-hezbollah-israel-escalates-attacks-trump-relax/"
    },
    {
      "title": "Cryptos Drop Amid Strategy's Bitcoin Sales, Suspended U.S.-Iran Talks",
      "source": "dpa_afx",
      "color": "#00e5ff",
      "timestamp": "2026-06-01T16:03:24+00:00",
      "timeDisplay": "4:03 PM",
      "link": "https://www.tradingview.com/news/dpa_afx:4a95bd51d08f8:0-cryptos-drop-amid-strategy-s-bitcoin-sales-suspended-u-s-iran-talks/"
    },
    {
      "title": "Oil Prices Soar as Iran Shuts Down US-Iran Ceasefire Negotiations",
      "source": "barchart",
      "color": "#00e5ff",
      "timestamp": "2026-06-01T16:03:18+00:00",
      "timeDisplay": "4:03 PM",
      "link": "https://www.tradingview.com/news/barchart:bee3a9658094b:0-oil-prices-soar-as-iran-shuts-down-us-iran-ceasefire-negotiations/"
    },
    {
      "title": "Bank of Canada's Credibility Faces Prolonged Test from Mideast \u2014 Market Talk",
      "source": "dow-jones",
      "color": "#00e5ff",
      "timestamp": "2026-06-01T16:03:00+00:00",
      "timeDisplay": "4:03 PM",
      "link": "https://www.tradingview.com/news/DJN_DN20260601006150:0/"
    },
    {
      "title": "Senators Cynthia Lummis, Tim Scott Press For CLARITY Act Passage \u2013 Reportedly Eye Push After July 4",
      "source": "stocktwits",
      "color": "#00e5ff",
      "timestamp": "2026-06-01T15:59:07+00:00",
      "timeDisplay": "3:59 PM",
      "link": "https://www.tradingview.com/news/stocktwits:f4dce616e094b:0-senators-cynthia-lummis-tim-scott-press-for-clarity-act-passage-reportedly-eye-push-after-july-4/"
    },
    {
      "title": "Hyperliquid Hits Record as ETFs Inflows Continue \u2014 Market Talk",
      "source": "dow-jones",
      "color": "#00e5ff",
      "timestamp": "2026-06-01T15:53:00+00:00",
      "timeDisplay": "3:53 PM",
      "link": "https://www.tradingview.com/news/DJN_DN20260601005943:0/"
    },
    {
      "title": "Are Ethereum OGs jumping ship? Here's what the data says",
      "source": "cointelegraph",
      "color": "#00e5ff",
      "timestamp": "2026-06-01T15:44:00+00:00",
      "timeDisplay": "3:44 PM",
      "link": "https://www.tradingview.com/news/cointelegraph:ea83203b2094b:0-are-ethereum-ogs-jumping-ship-here-s-what-the-data-says/"
    },
    {
      "title": "Gold Slides 2% on Firmer Dollar, Rising Crude \u2014 Market Talk",
      "source": "dow-jones",
      "color": "#00e5ff",
      "timestamp": "2026-06-01T15:26:00+00:00",
      "timeDisplay": "3:26 PM",
      "link": "https://www.tradingview.com/news/DJN_DN20260601005682:0/"
    },
    {
      "title": "Gold falls nearly 2% with inflation worries rising on Middle East conflict",
      "source": "moneycontrol",
      "color": "#00e5ff",
      "timestamp": "2026-06-01T15:25:54+00:00",
      "timeDisplay": "3:25 PM",
      "link": "https://www.tradingview.com/news/moneycontrol:ce65a7a75094b:0-gold-falls-nearly-2-with-inflation-worries-rising-on-middle-east-conflict/"
    },
    {
      "title": "US yields rise after report of Iran negotiation halt\u00a0",
      "source": "reuters",
      "color": "#ff6d00",
      "timestamp": "2026-06-01T15:24:23+00:00",
      "timeDisplay": "3:24 PM",
      "link": "https://www.tradingview.com/news/reuters.com,2026:newsml_L6N4290XI:0-us-yields-rise-after-report-of-iran-negotiation-halt/"
    },
    {
      "title": "Late May Woes Look to Extend Into June for Crypto \u2014 Market Talk",
      "source": "dow-jones",
      "color": "#00e5ff",
      "timestamp": "2026-06-01T15:17:00+00:00",
      "timeDisplay": "3:17 PM",
      "link": "https://www.tradingview.com/news/DJN_DN20260601005609:0/"
    },
    {
      "title": "Stalled U.S-Iran Peace Talks Rattle Global Markets",
      "source": "dpa_afx",
      "color": "#00e5ff",
      "timestamp": "2026-06-01T15:10:11+00:00",
      "timeDisplay": "3:10 PM",
      "link": "https://www.tradingview.com/news/dpa_afx:c4a38dcf81163:0-stalled-u-s-iran-peace-talks-rattle-global-markets/"
    },
    {
      "title": "Dollar Rises on Hawkish Rally in Oil Prices",
      "source": "barchart",
      "color": "#00e5ff",
      "timestamp": "2026-06-01T14:57:04+00:00",
      "timeDisplay": "2:57 PM",
      "link": "https://www.tradingview.com/news/barchart:2d07b133f094b:0-dollar-rises-on-hawkish-rally-in-oil-prices/"
    },
    {
      "title": "US ISM\u2019S SPENCE: US IS PROTECTED A LITTLE BIT FROM SUPPLY SHORTAGES OF MATERIALS VS. ASIA BUT HIGH PRICES CAN LEAD TO TIGHT SUPPLY AND IMPACT OUTPUT",
      "source": "macenews",
      "color": "#00e5ff",
      "timestamp": "2026-06-01T14:56:00+00:00",
      "timeDisplay": "2:56 PM",
      "link": "https://www.tradingview.com/news/macenews:c52e56a88094b:0-us-ism-s-spence-us-is-protected-a-little-bit-from-supply-shortages-of-materials-vs-asia-but-high-prices-can-lead-to-tight-supply-and-impact-output/"
    },
    {
      "title": "US ISM\u2019S SPENCE ON MANUFACTURING: PRICES ARE UP FOR JUST ABOUT EVERYTHING FROM COMPUTER CHIPS TO RESINS DUE TO MIDEAST WAR",
      "source": "macenews",
      "color": "#00e5ff",
      "timestamp": "2026-06-01T14:54:00+00:00",
      "timeDisplay": "2:54 PM",
      "link": "https://www.tradingview.com/news/macenews:4090d6a87094b:0-us-ism-s-spence-on-manufacturing-prices-are-up-for-just-about-everything-from-computer-chips-to-resins-due-to-mideast-war/"
    },
    {
      "title": "Money in Bitcoin ETFs Keep Flowing Out \u2014 Market Talk",
      "source": "dow-jones",
      "color": "#00e5ff",
      "timestamp": "2026-06-01T14:47:00+00:00",
      "timeDisplay": "2:47 PM",
      "link": "https://www.tradingview.com/news/DJN_DN20260601005280:0/"
    },
    {
      "title": "Dollar rises as markets parse fragile Middle East peace talks",
      "source": "reuters",
      "color": "#ff6d00",
      "timestamp": "2026-06-01T14:44:18+00:00",
      "timeDisplay": "2:44 PM",
      "link": "https://www.tradingview.com/news/reuters.com,2026:newsml_L1N4290G1:0-dollar-rises-as-markets-parse-fragile-middle-east-peace-talks/"
    },
    {
      "title": "Bitmine acquires 26,497 ETH as it targets a slower approach to 5% of Ethereum\u2019s total supply",
      "source": "the_block",
      "color": "#00e5ff",
      "timestamp": "2026-06-01T14:29:24+00:00",
      "timeDisplay": "2:29 PM",
      "link": "https://www.tradingview.com/news/the_block:5d0625707094b:0-bitmine-acquires-26-497-eth-as-it-targets-a-slower-approach-to-5-of-ethereum-s-total-supply/"
    },
    {
      "title": "US ISM\u2019S SPENCE TO REPORTERS ON MAY REPORT: I BELIEVE THERE\u2019S PENT-UP DEMAND HERE BOOSTING MANUFACTURING SECTOR",
      "source": "macenews",
      "color": "#00e5ff",
      "timestamp": "2026-06-01T14:29:00+00:00",
      "timeDisplay": "2:29 PM",
      "link": "https://www.tradingview.com/news/macenews:4a1306e7b094b:0-us-ism-s-spence-to-reporters-on-may-report-i-believe-there-s-pent-up-demand-here-boosting-manufacturing-sector/"
    },
    {
      "title": "US ISM\u2019S SPENCE: EMPLOYMENT SUBINDEX STILL LOW, PRICES HIGH BUT BOTH IN RIGHT DIRECTION, BEST COMBINATION SEEN IN A WHILE",
      "source": "macenews",
      "color": "#00e5ff",
      "timestamp": "2026-06-01T14:26:00+00:00",
      "timeDisplay": "2:26 PM",
      "link": "https://www.tradingview.com/news/macenews:5f34ef48e094b:0-us-ism-s-spence-employment-subindex-still-low-prices-high-but-both-in-right-direction-best-combination-seen-in-a-while/"
    },
    {
      "title": "US ISM\u2019S SPENCE: MOST OF NEW ORDER RISE IN MAY REFLECTS UNDERLYING DEMAND, DOES NOT SEEM DUE TO STOCKING UP IN ANTICIPATION OF MIDEAST DISRUPTIONS",
      "source": "macenews",
      "color": "#00e5ff",
      "timestamp": "2026-06-01T14:22:00+00:00",
      "timeDisplay": "2:22 PM",
      "link": "https://www.tradingview.com/news/macenews:6080a9c6b094b:0-us-ism-s-spence-most-of-new-order-rise-in-may-reflects-underlying-demand-does-not-seem-due-to-stocking-up-in-anticipation-of-mideast-disruptions/"
    },
    {
      "title": "US ISM MANUFACTURING REPORT: IRAN WAR STARTING TO HIT SUPPLY CHAIN DIRECTLY, RAISE COSTS, CAUSING SHIPMENT DELAYS, UNCERTAINTIES",
      "source": "macenews",
      "color": "#00e5ff",
      "timestamp": "2026-06-01T14:16:00+00:00",
      "timeDisplay": "2:16 PM",
      "link": "https://www.tradingview.com/news/macenews:5ab359f7a094b:0-us-ism-manufacturing-report-iran-war-starting-to-hit-supply-chain-directly-raise-costs-causing-shipment-delays-uncertainties/"
    },
    {
      "title": "Recovery hopes fade as Kelp DAO hacker launders nearly all $220M in stolen funds",
      "source": "cointelegraph",
      "color": "#00e5ff",
      "timestamp": "2026-06-01T14:09:52+00:00",
      "timeDisplay": "2:09 PM",
      "link": "https://www.tradingview.com/news/cointelegraph:39d1abcd2094b:0-recovery-hopes-fade-as-kelp-dao-hacker-launders-nearly-all-220m-in-stolen-funds/"
    },
    {
      "title": "Treasury Yields, Dollar Rise on Reports Tehran Is Exiting Talks \u2014 Market Talk",
      "source": "dow-jones",
      "color": "#00e5ff",
      "timestamp": "2026-06-01T14:09:00+00:00",
      "timeDisplay": "2:09 PM",
      "link": "https://www.tradingview.com/news/DJN_DN20260601004913:0/"
    },
    {
      "title": "US ISM MAY MANUFACTURING: 25% OF COMMENTS WERE POSITIVE, 69% NEGATIVE, WITH A 1-TO-2.7 RATIO OF POSITIVE TO NEGATIVE SENTIMENT",
      "source": "macenews",
      "color": "#00e5ff",
      "timestamp": "2026-06-01T14:07:00+00:00",
      "timeDisplay": "2:07 PM",
      "link": "https://www.tradingview.com/news/macenews:6e5c7caa8094b:0-us-ism-may-manufacturing-25-of-comments-were-positive-69-negative-with-a-1-to-2-7-ratio-of-positive-to-negative-sentiment/"
    },
    {
      "title": "US ISM: IRAN WAR MENTIONED IN 42% IN COMMENTS, TARIFFS IN 18%; 57% OF PANELISTS MENTIONED PRICING VOLATILITY AS AN ISSUE FOR THEIR COMPANIES",
      "source": "macenews",
      "color": "#00e5ff",
      "timestamp": "2026-06-01T14:07:00+00:00",
      "timeDisplay": "2:07 PM",
      "link": "https://www.tradingview.com/news/macenews:c6ce29369094b:0-us-ism-iran-war-mentioned-in-42-in-comments-tariffs-in-18-57-of-panelists-mentioned-pricing-volatility-as-an-issue-for-their-companies/"
    },
    {
      "title": "US ISM MANUFACTURING REPORT: NEW EXPORT ORDERS BACK TO EXPANSION AT 50.6 VS. 47.9 IN APRIL",
      "source": "macenews",
      "color": "#00e5ff",
      "timestamp": "2026-06-01T14:03:00+00:00",
      "timeDisplay": "2:03 PM",
      "link": "https://www.tradingview.com/news/macenews:8552c7d06094b:0-us-ism-manufacturing-report-new-export-orders-back-to-expansion-at-50-6-vs-47-9-in-april/"
    },
    {
      "title": "US ISM MANUFACTURING REPORT: MAY INDEX IS HIGHEST SINCE MAY 2022",
      "source": "macenews",
      "color": "#00e5ff",
      "timestamp": "2026-06-01T14:02:00+00:00",
      "timeDisplay": "2:02 PM",
      "link": "https://www.tradingview.com/news/macenews:475bbe13a094b:0-us-ism-manufacturing-report-may-index-is-highest-since-may-2022/"
    },
    {
      "title": "US APRIL CONSTRUCTION SPENDING +0.9% Y/Y",
      "source": "macenews",
      "color": "#00e5ff",
      "timestamp": "2026-06-01T14:01:00+00:00",
      "timeDisplay": "2:01 PM",
      "link": "https://www.tradingview.com/news/macenews:4682b095f094b:0-us-april-construction-spending-0-9-y-y/"
    },
    {
      "title": "US ISM MANUFACTURING EMPLOYMENT INDEX 48.6 IN MAY VS. 46.4 IN APRIL, 48.7 IN MARCH",
      "source": "macenews",
      "color": "#00e5ff",
      "timestamp": "2026-06-01T14:01:00+00:00",
      "timeDisplay": "2:01 PM",
      "link": "https://www.tradingview.com/news/macenews:79071726d094b:0-us-ism-manufacturing-employment-index-48-6-in-may-vs-46-4-in-april-48-7-in-march/"
    },
    {
      "title": "US ISM MANUFACTURING PRICES PAID INDEX 82.1 IN MAY VS. 84.6 IN APRIL, 78.3 IN MARCH",
      "source": "macenews",
      "color": "#00e5ff",
      "timestamp": "2026-06-01T14:01:00+00:00",
      "timeDisplay": "2:01 PM",
      "link": "https://www.tradingview.com/news/macenews:88afbeb81094b:0-us-ism-manufacturing-prices-paid-index-82-1-in-may-vs-84-6-in-april-78-3-in-march/"
    },
    {
      "title": "US ISM MANUFACTURING SUPPLIER DELIVERIES 60.6 INDEX IN MAY VS. 60.6 IN APRIL, 58.9 IN MARCH",
      "source": "macenews",
      "color": "#00e5ff",
      "timestamp": "2026-06-01T14:01:00+00:00",
      "timeDisplay": "2:01 PM",
      "link": "https://www.tradingview.com/news/macenews:2461cc6a0094b:0-us-ism-manufacturing-supplier-deliveries-60-6-index-in-may-vs-60-6-in-april-58-9-in-march/"
    },
    {
      "title": "US APRIL CONSTRUCTION SPENDING +0.4% VS +0.3% EXPECTED",
      "source": "macenews",
      "color": "#00e5ff",
      "timestamp": "2026-06-01T14:00:00+00:00",
      "timeDisplay": "2:00 PM",
      "link": "https://www.tradingview.com/news/macenews:756c1c354094b:0-us-april-construction-spending-0-4-vs-0-3-expected/"
    },
    {
      "title": "US ISM MANUFACTURING INDEX 54.0 IN MAY VS. 52.7 IN APRIL, 52.7 IN MARCH (VS. 53.1 MARKETS EXPECTED FOR MAY)",
      "source": "macenews",
      "color": "#00e5ff",
      "timestamp": "2026-06-01T14:00:00+00:00",
      "timeDisplay": "2:00 PM",
      "link": "https://www.tradingview.com/news/macenews:36d4b20ef094b:0-us-ism-manufacturing-index-54-0-in-may-vs-52-7-in-april-52-7-in-march-vs-53-1-markets-expected-for-may/"
    },
    {
      "title": "US ISM MANUFACTURING NEW ORDERS INDEX 56.8 IN MAY VS. 54.1 IN APRIL, 53.5 IN MARCH",
      "source": "macenews",
      "color": "#00e5ff",
      "timestamp": "2026-06-01T14:00:00+00:00",
      "timeDisplay": "2:00 PM",
      "link": "https://www.tradingview.com/news/macenews:9f0291b74094b:0-us-ism-manufacturing-new-orders-index-56-8-in-may-vs-54-1-in-april-53-5-in-march/"
    },
    {
      "title": "Gold declines Rs 2,500 to Rs 1.6 lakh/10g amid fresh US-Iran tensions",
      "source": "moneycontrol",
      "color": "#00e5ff",
      "timestamp": "2026-06-01T13:56:57+00:00",
      "timeDisplay": "1:56 PM",
      "link": "https://www.tradingview.com/news/moneycontrol:06b6d1e12094b:0-gold-declines-rs-2-500-to-rs-1-6-lakh-10g-amid-fresh-us-iran-tensions/"
    }
  ]
}